{"err":0,"desc":"ERR_NONE","dat":{"title":[{"title":"id"},{"title":"Timestamp"},{"title":"SN"},{"title":"Grid Voltage","unit":"V"},{"title":"Grid Frequency","unit":"Hz"},{"title":"PV Input Voltage","unit":"V"},{"title":"Battery Voltage","unit":"V"},{"title":"Battery Capacity","unit":"%"},{"title":"Battery Charging Current","unit":"A"},{"title":"Battery Discharge Current","unit":"A"},{"title":"AC Output Voltage","unit":"V"},{"title":"AC Output Frequency","unit":"Hz"},{"title":"AC Output Apparent Power","unit":"VA"},{"title":"AC Output Active Power","unit":"W"},{"title":"Output Load Percent","unit":"%"},{"title":"Machine Type"},{"title":"Main CPU Firmware Version"},{"title":"Grid Rating Voltage","unit":"V"},{"title":"Grid Rating Current","unit":"A"},{"title":"Battery Rating Voltage","unit":"V"},{"title":"AC Output Rating Voltage","unit":"V"},{"title":"AC Output Rating Current","unit":"A"},{"title":"AC Output Rating Frequency","unit":"Hz"},{"title":"AC Output Rating Apparent Power","unit":"VA"},{"title":"AC Output Rating Active Power","unit":"W"},{"title":"Battery Charge Voltage","unit":"V"},{"title":"Bulk Charging Voltage","unit":"V"},{"title":"Float Charging Voltage","unit":"V"},{"title":"Battery Type"},{"title":"Max. AC Charging Current","unit":"A"},{"title":"Max. Charging Current","unit":"A"},{"title":"AC Input Range"},{"title":"Output Source Priority"},{"title":"Charger Source Priority"},{"title":"Parallel Max Number"},{"title":"Battery Discharge Voltage","unit":"V"},{"title":"BUS Voltage","unit":"v"},{"title":"PV Input Current For Battery","unit":"A"},{"title":"Battery Voltage From SCC","unit":"V"},{"title":"Load Status"},{"title":"Charging Status"},{"title":"Battery Voltage Offset ","unit":"V"},{"title":"PV Power","unit":"W"},{"title":"Model"}],"row":[{"realtime":true,"field":["3d5d33cab17fefb11bd4220cb1b23ae7","2023-08-24 00:00:26","92932010100438","232.6","50.4","0.0","0.6","0","0","0","232.6","50.4","1232","1218","22","Grid Tie","00075.04","230.0","23.9","48.0","230.0","23.9","50.0","5500","5500","46.0","56.4","54.0","USER","40","60","UPS","SUB","CSO","9","54.0","324","0","0.0","Load on","Do Nothing","0","0","Line Mode"]},{"realtime":true,"field":["3d28656f04896d025491a2b9b0cf5367","2023-08-24 00:05:33","92932010100438","231.0","50.2","0.0","0.6","0","0","0","231.0","50.2","1246","1237","22","Grid Tie","00075.04","230.0","23.9","48.0","230.0","23.9","50.0","5500","5500","46.0","56.4","54.0","USER","40","60","UPS","SUB","CSO","9","54.0","322","0","0.0","Load on","Do Nothing","0","0","Line Mode"]},{"realtime":true,"field":["57fd216b79ffc2eb79d21d232f835981","2023-08-24 00:11:20","92932010100438","230.4","50.1","0.0","0.6","0","0","0","230.4","50.1","1244","1234","22","Grid Tie","00075.04","230.0","23.9","48.0","230.0","23.9","50.0","5500","5500","46.0","56.4","54.0","USER","40","60","UPS","SUB","CSO","9","54.0","321","0","0.0","Load on","Do Nothing","0","0","Line Mode"]},{"realtime":true,"field":["75abc8c32eec70917f2bd605c5a365ff","2023-08-24 00:16:51","92932010100438","233.2","50.2","0.0","0.6","0","0","0","233.2","50.2","1235","1226","22","Grid Tie","00075.04","230.0","23.9","48.0","230.0","23.9","50.0","5500","5500","46.0","56.4","54.0","USER","40","60","UPS","SUB","CSO","9","54.0","325","0","0.0","Load on","Do Nothing","0","0","Line Mode"]},{"realtime":true,"field":["1201996b979ea36c62ef8e7e9cc3fa68","2023-08-24 00:22:09","92932010100438","233.8","50.4","0.0","0.6","0","0","0","233.8","50.4","1215","1184","22","Grid Tie","00075.04","230.0","23.9","48.0","230.0","23.9","50.0","5500","5500","46.0","56.4","54.0","USER","40","60","UPS","SUB","CSO","9","54.0","326","0","0.0","Load on","Do Nothing","0","0","Line Mode"]},{"realtime":true,"field":["12ec2608fcfa91380054708b7b9ea77b","2023-08-24 00:27:11","92932010100438","233.3","50.2","0.0","0.6","0","0","0","233.3","50.2","1213","1201","22","Grid Tie","00075.04","230.0","23.9","48.0","230.0","23.9","50.0","5500","5500","46.0","56.4","54.0","USER","40","60","UPS","SUB","CSO","9","54.0","326","0","0.0","Load on","Do Nothing","0","0","Line Mode"]},{"realtime":true,"field":["2a3427c1652d595571dced3f88d44205","2023-08-24 00:32:15","92932010100438","233.6","50.3","0.0","0.6","0","0","0","233.6","50.3","1247","1247","22","Grid Tie","00075.04","230.0","23.9","48.0","230.0","23.9","50.0","5500","5500","46.0","56.4","54.0","USER","40","60","UPS","SUB","CSO","9","54.0","326","0","0.0","Load on","Do Nothing","0","0","Line Mode"]},{"realtime":true,"field":["4cfe3f8ba52b8a4a3d05d74d6db831fe","2023-08-24 00:38:43","92932010100438","235.9","50.5","0.0","0.6","0","0","0","235.9","50.5","212","202","3","Grid Tie","00075.04","230.0","23.9","48.0","230.0","23.9","50.0","5500","5500","46.0","56.4","54.0","USER","40","60","UPS","SUB","CSO","9","54.0","329","0","0.0","Load on","Do Nothing","0","0","Line Mode"]},{"realtime":true,"field":["5c1a18a3dabaa902648de81d1f5f0e47","2023-08-24 00:43:58","92932010100438","230.9","49.8","0.0","0.6","0","0","0","230.9","49.8","461","414","8","Grid Tie","00075.04","230.0","23.9","48.0","230.0","23.9","50.0","5500","5500","46.0","56.4","54.0","USER","40","60","UPS","SUB","CSO","9","54.0","322","0","0.0","Load on","Do Nothing","0","0","Line Mode"]},{"realtime":true,"field":["2427ee5b6f43e1d434ed2138a12976e7","2023-08-24 00:48:58","92932010100438","229.2","50.2","0.0","0.6","0","0","0","229.2","50.2","1214","1183","22","Grid Tie","00075.04","230.0","23.9","48.0","230.0","23.9","50.0","5500","5500","46.0","56.4","54.0","USER","40","60","UPS","SUB","CSO","9","54.0","320","0","0.0","Load on","Do Nothing","0","0","Line Mode"]},{"realtime":true,"field":["34169eaeed613fc46a3169ce8b96be15","2023-08-24 00:54:05","92932010100438","229.5","50.0","0.0","0.6","0","0","0","229.5","50.0","1606","1595","29","Grid Tie","00075.04","230.0","23.9","48.0","230.0","23.9","50.0","5500","5500","46.0","56.4","54.0","USER","40","60","UPS","SUB","CSO","9","54.0","320","0","0.0","Load on","Do Nothing","0","0","Line Mode"]},{"realtime":true,"field":["40720093d0113b595713a99fcbf153fa","2023-08-24 00:59:12","92932010100438","229.8","49.8","0.0","0.6","0","0","0","229.8","49.8","1379","1373","25","Grid Tie","00075.04","230.0","23.9","48.0","230.0","23.9","50.0","5500","5500","46.0","56.4","54.0","USER","40","60","UPS","SUB","CSO","9","54.0","320","0","0.0","Load on","Do Nothing","0","0","Line Mode"]},{"realtime":true,"field":["24e221d7090ba7d82c5ae19ca3391125","2023-08-24 01:04:17","92932010100438","230.5","50.2","0.0","0.7","0","0","0","230.5","50.2","1383","1357","25","Grid Tie","00075.04","230.0","23.9","48.0","230.0","23.9","50.0","5500","5500","46.0","56.4","54.0","USER","40","60","UPS","SUB","CSO","9","54.0","322","0","0.0","Load on","Do Nothing","0","0","Line Mode"]},{"realtime":true,"field":["155215ac8d389bd5277232712352c14a","2023-08-24 01:09:25","92932010100438","231.8","50.2","0.0","0.6","0","0","0","231.8","50.2","1205","1171","21","Grid Tie","00075.04","230.0","23.9","48.0","230.0","23.9","50.0","5500","5500","46.0","56.4","54.0","USER","40","60","UPS","SUB","CSO","9","54.0","323","0","0.0","Load on","Do Nothing","0","0","Line Mode"]},{"realtime":true,"field":["2795322ce35542bb38d072a7cfdacb3f","2023-08-24 01:14:28","92932010100438","232.7","50.2","0.0","0.6","0","0","0","232.7","50.2","1186","1162","21","Grid Tie","00075.04","230.0","23.9","48.0","230.0","23.9","50.0","5500","5500","46.0","56.4","54.0","USER","40","60","UPS","SUB","CSO","9","54.0","324","0","0.0","Load on","Do Nothing","0","0","Line Mode"]},{"realtime":true,"field":["52c048a395e8216846260e576385a028","2023-08-24 01:19:45","92932010100438","232.7","50.2","0.0","0.6","0","0","0","232.7","50.2","1256","1237","22","Grid Tie","00075.04","230.0","23.9","48.0","230.0","23.9","50.0","5500","5500","46.0","56.4","54.0","USER","40","60","UPS","SUB","CSO","9","54.0","324","0","0.0","Load on","Do Nothing","0","0","Line Mode"]},{"realtime":true,"field":["448fb0b1247ed7cc147e336298b16dde","2023-08-24 01:25:13","92932010100438","233.2","50.3","0.0","0.7","0","0","0","233.2","50.3","1253","1253","22","Grid Tie","00075.04","230.0","23.9","48.0","230.0","23.9","50.0","5500","5500","46.0","56.4","54.0","USER","40","60","UPS","SUB","CSO","9","54.0","325","0","0.0","Load on","Do Nothing","0","0","Line Mode"]},{"realtime":true,"field":["1cf6732e874dac106e9ba167a25b22ff","2023-08-24 01:30:17","92932010100438","233.3","50.4","0.0","0.5","0","0","0","233.3","50.4","1255","1255","22","Grid Tie","00075.04","230.0","23.9","48.0","230.0","23.9","50.0","5500","5500","46.0","56.4","54.0","USER","40","60","UPS","SUB","CSO","9","54.0","325","0","0.0","Load on","Do Nothing","0","0","Line Mode"]},{"realtime":true,"field":["65d33292da2eea6759f1e041790d04ae","2023-08-24 01:35:17","92932010100438","234.4","50.4","0.0","0.6","0","0","0","234.4","50.4","1242","1222","22","Grid Tie","00075.04","230.0","23.9","48.0","230.0","23.9","50.0","5500","5500","46.0","56.4","54.0","USER","40","60","UPS","SUB","CSO","9","54.0","327","0","0.0","Load on","Do Nothing","0","0","Line Mode"]},{"realtime":true,"field":["5890e3317b14083278baeb8bb2aba731","2023-08-24 01:40:31","92932010100438","234.3","50.4","0.0","0.6","0","0","0","234.3","50.4","1241","1177","22","Grid Tie","00075.04","230.0","23.9","48.0","230.0","23.9","50.0","5500","5500","46.0","56.4","54.0","USER","40","60","UPS","SUB","CSO","9","54.0","327","0","0.0","Load on","Do Nothing","0","0","Line Mode"]},{"realtime":true,"field":["66eabd57f9c305e06ea4476909db815e","2023-08-24 01:45:40","92932010100438","233.2","50.2","0.0","0.6","0","0","0","233.2","50.2","1282","1264","23","Grid Tie","00075.04","230.0","23.9","48.0","230.0","23.9","50.0","5500","5500","46.0","56.4","54.0","USER","40","60","UPS","SUB","CSO","9","54.0","325","0","0.0","Load on","Do Nothing","0","0","Line Mode"]},{"realtime":true,"field":["026900219f3a2722731a5770f15777d8","2023-08-24 01:51:06","92932010100438","233.4","49.9","0.0","0.6","0","0","0","233.4","49.9","934","931","16","Grid Tie","00075.04","230.0","23.9","48.0","230.0","23.9","50.0","5500","5500","46.0","56.4","54.0","USER","40","60","UPS","SUB","CSO","9","54.0","326","0","0.0","Load on","Do Nothing","0","0","Line Mode"]},{"realtime":true,"field":["17a9c43c97c016b01164f0c5d7654d33","2023-08-24 01:56:15","92932010100438","231.6","49.5","0.0","0.6","0","0","0","231.6","49.5","913","913","16","Grid Tie","00075.04","230.0","23.9","48.0","230.0","23.9","50.0","5500","5500","46.0","56.4","54.0","USER","40","60","UPS","SUB","CSO","9","54.0","323","0","0.0","Load on","Do Nothing","0","0","Line Mode"]},{"realtime":true,"field":["01cbe9449792a3f84e0a0c812004dc31","2023-08-24 02:01:35","92932010100438","233.1","49.6","0.0","0.5","0","0","0","233.1","49.6","779","779","14","Grid Tie","00075.04","230.0","23.9","48.0","230.0","23.9","50.0","5500","5500","46.0","56.4","54.0","USER","40","60","UPS","SUB","CSO","9","54.0","325","0","0.0","Load on","Do Nothing","0","0","Line Mode"]},{"realtime":true,"field":["5dbdbcea003a36ea3adae80f1bcc048e","2023-08-24 02:06:59","92932010100438","233.1","49.7","0.0","0.6","0","0","0","233.1","49.7","851","851","15","Grid Tie","00075.04","230.0","23.9","48.0","230.0","23.9","50.0","5500","5500","46.0","56.4","54.0","USER","40","60","UPS","SUB","CSO","9","54.0","325","0","0.0","Load on","Do Nothing","0","0","Line Mode"]},{"realtime":true,"field":["3f2ede37cfe2eba95dcb7ac401127445","2023-08-24 02:12:16","92932010100438","235.1","50.0","0.0","0.6","0","0","0","235.1","50.0","799","792","14","Grid Tie","00075.04","230.0","23.9","48.0","230.0","23.9","50.0","5500","5500","46.0","56.4","54.0","USER","40","60","UPS","SUB","CSO","9","54.0","328","0","0.0","Load on","Do Nothing","0","0","Line Mode"]},{"realtime":true,"field":["151504e460b348a62edc7ba4ec84c2f3","2023-08-24 02:17:13","92932010100438","235.9","50.1","0.0","0.6","0","0","0","235.9","50.1","890","890","16","Grid Tie","00075.04","230.0","23.9","48.0","230.0","23.9","50.0","5500","5500","46.0","56.4","54.0","USER","40","60","UPS","SUB","CSO","9","54.0","329","0","0.0","Load on","Do Nothing","0","0","Line Mode"]},{"realtime":true,"field":["32e972755084b16449bce5c942c41abf","2023-08-24 02:22:55","92932010100438","236.8","50.2","0.0","0.6","0","0","0","236.8","50.2","836","836","15","Grid Tie","00075.04","230.0","23.9","48.0","230.0","23.9","50.0","5500","5500","46.0","56.4","54.0","USER","40","60","UPS","SUB","CSO","9","54.0","330","0","0.0","Load on","Do Nothing","0","0","Line Mode"]},{"realtime":true,"field":["5e56e7adab7efaa93e99e4023bb7b189","2023-08-24 02:28:00","92932010100438","238.8","50.4","0.0","0.6","0","0","0","238.8","50.4","883","880","16","Grid Tie","00075.04","230.0","23.9","48.0","230.0","23.9","50.0","5500","5500","46.0","56.4","54.0","USER","40","60","UPS","SUB","CSO","9","54.0","333","0","0.0","Load on","Do Nothing","0","0","Line Mode"]},{"realtime":true,"field":["416f2f7b50f99f1a6bed00ea5d7c284a","2023-08-24 02:32:55","92932010100438","238.3","50.3","0.0","0.6","0","0","0","238.3","50.3","914","914","16","Grid Tie","00075.04","230.0","23.9","48.0","230.0","23.9","50.0","5500","5500","46.0","56.4","54.0","USER","40","60","UPS","SUB","CSO","9","54.0","332","0","0.0","Load on","Do Nothing","0","0","Line Mode"]},{"realtime":true,"field":["608c01dedbe3c0a575bdecbeff1fb3f9","2023-08-24 02:38:22","92932010100438","238.3","50.3","0.0","0.7","0","0","0","238.3","50.3","840","840","15","Grid Tie","00075.04","230.0","23.9","48.0","230.0","23.9","50.0","5500","5500","46.0","56.4","54.0","USER","40","60","UPS","SUB","CSO","9","54.0","332","0","0.0","Load on","Do Nothing","0","0","Line Mode"]},{"realtime":true,"field":["39ceb219745a9dcb72f3640ed6190945","2023-08-24 02:43:30","92932010100438","238.6","50.4","0.0","0.6","0","0","0","238.6","50.4","837","837","15","Grid Tie","00075.04","230.0","23.9","48.0","230.0","23.9","50.0","5500","5500","46.0","56.4","54.0","USER","40","60","UPS","SUB","CSO","9","54.0","333","0","0.0","Load on","Do Nothing","0","0","Line Mode"]},{"realtime":true,"field":["7fec1eb312bf6f8d46f578b6226c08dd","2023-08-24 02:48:52","92932010100438","239.4","50.3","0.0","0.6","0","0","0","239.4","50.3","938","938","17","Grid Tie","00075.04","230.0","23.9","48.0","230.0","23.9","50.0","5500","5500","46.0","56.4","54.0","USER","40","60","UPS","SUB","CSO","9","54.0","334","0","0.0","Load on","Do Nothing","0","0","Line Mode"]},{"realtime":true,"field":["39aac43c21fa7b243219eaccfcbe9e1d","2023-08-24 02:54:08","92932010100438","239.1","50.3","0.0","0.6","0","0","0","239.1","50.3","900","900","16","Grid Tie","00075.04","230.0","23.9","48.0","230.0","23.9","50.0","5500","5500","46.0","56.4","54.0","USER","40","60","UPS","SUB","CSO","9","54.0","334","0","0.0","Load on","Do Nothing","0","0","Line Mode"]},{"realtime":true,"field":["320ab05b9e0a60024f61f0521f2e7a79","2023-08-24 02:59:30","92932010100438","238.1","50.2","0.0","0.6","0","0","0","238.1","50.2","785","783","14","Grid Tie","00075.04","230.0","23.9","48.0","230.0","23.9","50.0","5500","5500","46.0","56.4","54.0","USER","40","60","UPS","SUB","CSO","9","54.0","332","0","0.0","Load on","Do Nothing","0","0","Line Mode"]},{"realtime":true,"field":["10e50604d58a5b8a1bfd02ed8827883c","2023-08-24 03:04:36","92932010100438","237.9","49.9","0.0","0.6","0","0","0","237.9","49.9","769","769","13","Grid Tie","00075.04","230.0","23.9","48.0","230.0","23.9","50.0","5500","5500","46.0","56.4","54.0","USER","40","60","UPS","SUB","CSO","9","54.0","332","0","0.0","Load on","Do Nothing","0","0","Line Mode"]},{"realtime":true,"field":["493c36916d2b736311321f88ae98457a","2023-08-24 03:09:45","92932010100438","237.3","49.8","0.0","0.6","0","0","0","237.3","49.8","1353","1351","24","Grid Tie","00075.04","230.0","23.9","48.0","230.0","23.9","50.0","5500","5500","46.0","56.4","54.0","USER","40","60","UPS","SUB","CSO","9","54.0","330","0","0.0","Load on","Do Nothing","0","0","Line Mode"]},{"realtime":true,"field":["1ba2f8bc1da40bbd27af369ae2410310","2023-08-24 03:14:54","92932010100438","237.8","49.8","0.0","0.6","0","0","0","237.8","49.8","889","889","16","Grid Tie","00075.04","230.0","23.9","48.0","230.0","23.9","50.0","5500","5500","46.0","56.4","54.0","USER","40","60","UPS","SUB","CSO","9","54.0","332","0","0.0","Load on","Do Nothing","0","0","Line Mode"]},{"realtime":true,"field":["32591ee38dc48752045b2fb8518a5aeb","2023-08-24 03:19:54","92932010100438","237.2","49.8","0.0","0.6","0","0","0","237.2","49.8","761","761","13","Grid Tie","00075.04","230.0","23.9","48.0","230.0","23.9","50.0","5500","5500","46.0","56.4","54.0","USER","40","60","UPS","SUB","CSO","9","54.0","330","0","0.0","Load on","Do Nothing","0","0","Line Mode"]},{"realtime":true,"field":["54788ff4da10e1641bf99c6a1a9341c4","2023-08-24 03:25:02","92932010100438","236.8","49.7","0.0","0.6","0","0","0","236.8","49.7","804","800","14","Grid Tie","00075.04","230.0","23.9","48.0","230.0","23.9","50.0","5500","5500","46.0","56.4","54.0","USER","40","60","UPS","SUB","CSO","9","54.0","330","0","0.0","Load on","Do Nothing","0","0","Line Mode"]},{"realtime":true,"field":["513551a62383082667ee1e0ad750b01a","2023-08-24 03:30:01","92932010100438","237.1","49.8","0.0","0.6","0","0","0","237.1","49.8","765","765","13","Grid Tie","00075.04","230.0","23.9","48.0","230.0","23.9","50.0","5500","5500","46.0","56.4","54.0","USER","40","60","UPS","SUB","CSO","9","54.0","330","0","0.0","Load on","Do Nothing","0","0","Line Mode"]},{"realtime":true,"field":["1ef640d27870ab1016840b816704fe91","2023-08-24 03:35:02","92932010100438","238.2","50.0","0.0","0.6","0","0","0","238.2","50.0","834","773","15","Grid Tie","00075.04","230.0","23.9","48.0","230.0","23.9","50.0","5500","5500","46.0","56.4","54.0","USER","40","60","UPS","SUB","CSO","9","54.0","332","0","0.0","Load on","Do Nothing","0","0","Line Mode"]},{"realtime":true,"field":["7e014f1f6ad6c3b5157e1fbf0192ea89","2023-08-24 03:40:19","92932010100438","239.1","50.2","0.0","0.7","0","0","0","239.1","50.2","821","821","14","Grid Tie","00075.04","230.0","23.9","48.0","230.0","23.9","50.0","5500","5500","46.0","56.4","54.0","USER","40","60","UPS","SUB","CSO","9","54.0","333","0","0.0","Load on","Do Nothing","0","0","Line Mode"]},{"realtime":true,"field":["1772c399bb3a31ce365a080579c51f56","2023-08-24 03:45:19","92932010100438","238.4","50.0","0.0","0.6","0","0","0","238.4","50.0","858","761","15","Grid Tie","00075.04","230.0","23.9","48.0","230.0","23.9","50.0","5500","5500","46.0","56.4","54.0","USER","40","60","UPS","SUB","CSO","9","54.0","332","0","0.0","Load on","Do Nothing","0","0","Line Mode"]},{"realtime":true,"field":["31364b3bfc4c91c208638bcbcc553666","2023-08-24 03:50:16","92932010100438","241.0","50.2","0.0","0.6","0","0","0","241.0","50.2","197","197","3","Grid Tie","00075.04","230.0","23.9","48.0","230.0","23.9","50.0","5500","5500","46.0","56.4","54.0","USER","40","60","UPS","SUB","CSO","9","54.0","336","0","0.0","Load on","Do Nothing","0","0","Line Mode"]},{"realtime":true,"field":["62e2511fd1da1aaa4a940eb92f677a60","2023-08-24 03:55:21","92932010100438","241.7","50.2","0.0","0.6","0","0","0","241.7","50.2","198","198","3","Grid Tie","00075.04","230.0","23.9","48.0","230.0","23.9","50.0","5500","5500","46.0","56.4","54.0","USER","40","60","UPS","SUB","CSO","9","54.0","337","0","0.0","Load on","Do Nothing","0","0","Line Mode"]},{"realtime":true,"field":["3b95fea4fe75f9d773adee322ee56d70","2023-08-24 04:00:51","92932010100438","241.1","50.4","0.0","0.6","0","0","0","241.1","50.4","200","200","3","Grid Tie","00075.04","230.0","23.9","48.0","230.0","23.9","50.0","5500","5500","46.0","56.4","54.0","USER","40","60","UPS","SUB","CSO","9","54.0","336","0","0.0","Load on","Do Nothing","0","0","Line Mode"]},{"realtime":true,"field":["41c9e2d6333779287a1dd358c06ad1f9","2023-08-24 04:06:15","92932010100438","239.5","50.3","0.0","0.6","0","0","0","239.5","50.3","197","197","3","Grid Tie","00075.04","230.0","23.9","48.0","230.0","23.9","50.0","5500","5500","46.0","56.4","54.0","USER","40","60","UPS","SUB","CSO","9","54.0","334","0","0.0","Load on","Do Nothing","0","0","Line Mode"]},{"realtime":true,"field":["27ab36063ca0de70425d6a2362882548","2023-08-24 04:11:56","92932010100438","238.3","50.1","0.0","0.6","0","0","0","238.3","50.1","197","197","3","Grid Tie","00075.04","230.0","23.9","48.0","230.0","23.9","50.0","5500","5500","46.0","56.4","54.0","USER","40","60","UPS","SUB","CSO","9","54.0","332","0","0.0","Load on","Do Nothing","0","0","Line Mode"]},{"realtime":true,"field":["748566a6ba70ec457ba058d6fe26e77a","2023-08-24 04:17:51","92932010100438","236.8","50.0","0.0","0.6","0","0","0","236.8","50.0","745","745","13","Grid Tie","00075.04","230.0","23.9","48.0","230.0","23.9","50.0","5500","5500","46.0","56.4","54.0","USER","40","60","UPS","SUB","CSO","9","54.0","330","0","0.0","Load on","Do Nothing","0","0","Line Mode"]},{"realtime":true,"field":["7e5fae5379063d17029ea680151fc965","2023-08-24 04:23:42","92932010100438","236.3","49.9","0.0","0.6","0","0","0","236.3","49.9","839","839","15","Grid Tie","00075.04","230.0","23.9","48.0","230.0","23.9","50.0","5500","5500","46.0","56.4","54.0","USER","40","60","UPS","SUB","CSO","9","54.0","329","0","0.0","Load on","Do Nothing","0","0","Line Mode"]},{"realtime":true,"field":["3d8284caaa11dc805329d2c67dbfe14c","2023-08-24 04:29:30","92932010100438","236.2","49.9","0.0","0.6","0","0","0","236.2","49.9","772","772","14","Grid Tie","00075.04","230.0","23.9","48.0","230.0","23.9","50.0","5500","5500","46.0","56.4","54.0","USER","40","60","UPS","SUB","CSO","9","54.0","329","0","0.0","Load on","Do Nothing","0","0","Line Mode"]},{"realtime":true,"field":["1769a090f9d8a8873594663ae611de2a","2023-08-24 04:35:20","92932010100438","236.0","50.0","0.0","0.6","0","0","0","236.0","50.0","755","750","13","Grid Tie","00075.04","230.0","23.9","48.0","230.0","23.9","50.0","5500","5500","46.0","56.4","54.0","USER","40","60","UPS","SUB","CSO","9","54.0","329","0","0.0","Load on","Do Nothing","0","0","Line Mode"]},{"realtime":true,"field":["4cd87a44dcbfa21e64db96e59e7bd2f5","2023-08-24 04:41:25","92932010100438","236.9","50.2","0.0","0.6","0","0","0","236.9","50.2","736","736","13","Grid Tie","00075.04","230.0","23.9","48.0","230.0","23.9","50.0","5500","5500","46.0","56.4","54.0","USER","40","60","UPS","SUB","CSO","9","54.0","330","0","0.0","Load on","Do Nothing","0","0","Line Mode"]},{"realtime":true,"field":["63af55567a4eda605339ef1607f8f0d5","2023-08-24 04:47:04","92932010100438","238.1","50.4","0.0","0.6","0","0","0","238.1","50.4","833","833","15","Grid Tie","00075.04","230.0","23.9","48.0","230.0","23.9","50.0","5500","5500","46.0","56.4","54.0","USER","40","60","UPS","SUB","CSO","9","54.0","332","0","0.0","Load on","Do Nothing","0","0","Line Mode"]},{"realtime":true,"field":["546e307eb9bb5bc02726f6ce8ea42e44","2023-08-24 04:53:08","92932010100438","235.5","49.9","0.0","0.6","0","0","0","235.5","49.9","777","770","14","Grid Tie","00075.04","230.0","23.9","48.0","230.0","23.9","50.0","5500","5500","46.0","56.4","54.0","USER","40","60","UPS","SUB","CSO","9","54.0","328","0","0.0","Load on","Do Nothing","0","0","Line Mode"]},{"realtime":true,"field":["2ae8d70556f904353fd2dfdcf1dad959","2023-08-24 04:58:57","92932010100438","235.9","49.9","0.0","0.6","0","0","0","235.9","49.9","197","197","3","Grid Tie","00075.04","230.0","23.9","48.0","230.0","23.9","50.0","5500","5500","46.0","56.4","54.0","USER","40","60","UPS","SUB","CSO","9","54.0","329","0","0.0","Load on","Do Nothing","0","0","Line Mode"]},{"realtime":true,"field":["6d66bff813e1332228253ac2e72549e6","2023-08-24 05:05:19","92932010100438","235.1","49.5","0.0","0.6","0","0","0","235.1","49.5","192","192","3","Grid Tie","00075.04","230.0","23.9","48.0","230.0","23.9","50.0","5500","5500","46.0","56.4","54.0","USER","40","60","UPS","SUB","CSO","9","54.0","327","0","0.0","Load on","Do Nothing","0","0","Line Mode"]},{"realtime":true,"field":["062046f2f8001faa42df667ab602dd97","2023-08-24 05:10:45","92932010100438","234.6","49.6","0.0","0.6","0","0","0","234.6","49.6","197","197","3","Grid Tie","00075.04","230.0","23.9","48.0","230.0","23.9","50.0","5500","5500","46.0","56.4","54.0","USER","40","60","UPS","SUB","CSO","9","54.0","327","0","0.0","Load on","Do Nothing","0","0","Line Mode"]},{"realtime":true,"field":["2fc2c08cc0b9ae3d059d594d46bd7aa7","2023-08-24 05:15:46","92932010100438","234.9","49.9","0.0","0.6","0","0","0","234.9","49.9","194","194","3","Grid Tie","00075.04","230.0","23.9","48.0","230.0","23.9","50.0","5500","5500","46.0","56.4","54.0","USER","40","60","UPS","SUB","CSO","9","54.0","327","0","0.0","Load on","Do Nothing","0","0","Line Mode"]},{"realtime":true,"field":["48148167d311cefe5bf4095d17a47f7b","2023-08-24 05:21:19","92932010100438","236.3","49.9","0.0","0.6","0","0","0","236.3","49.9","175","175","3","Grid Tie","00075.04","230.0","23.9","48.0","230.0","23.9","50.0","5500","5500","46.0","56.4","54.0","USER","40","60","UPS","SUB","CSO","9","54.0","329","0","0.0","Load on","Do Nothing","0","0","Line Mode"]},{"realtime":true,"field":["52d2aab075f9ae1f2a49e533566352fe","2023-08-24 05:26:44","92932010100438","235.5","50.0","0.0","0.6","0","0","0","235.5","50.0","147","147","2","Grid Tie","00075.04","230.0","23.9","48.0","230.0","23.9","50.0","5500","5500","46.0","56.4","54.0","USER","40","60","UPS","SUB","CSO","9","54.0","328","0","0.0","Load on","Do Nothing","0","0","Line Mode"]},{"realtime":true,"field":["615a1e94cecd5c9746071a2267ad9b87","2023-08-24 05:31:53","92932010100438","235.3","50.2","127.7","0.6","0","0","0","235.3","50.2","143","143","2","Grid Tie","00075.04","230.0","23.9","48.0","230.0","23.9","50.0","5500","5500","46.0","56.4","54.0","USER","40","60","UPS","SUB","CSO","9","54.0","368","0","0.0","Load on","--","0","22","Line Mode"]},{"realtime":true,"field":["1ce8b8277ec695fb6cb2dc2ecaf4eb85","2023-08-24 05:36:54","92932010100438","235.0","50.4","133.4","0.7","0","0","0","235.0","50.4","143","143","2","Grid Tie","00075.04","230.0","23.9","48.0","230.0","23.9","50.0","5500","5500","46.0","56.4","54.0","USER","40","60","UPS","SUB","CSO","9","54.0","369","0","0.0","Load on","--","0","26","Line Mode"]},{"realtime":true,"field":["561dc1048bbf2e2c727a813c9f593a57","2023-08-24 05:41:55","92932010100438","233.4","50.2","129.2","0.7","0","0","0","233.4","50.2","280","273","5","Grid Tie","00075.04","230.0","23.9","48.0","230.0","23.9","50.0","5500","5500","46.0","56.4","54.0","USER","40","60","UPS","SUB","CSO","9","54.0","366","0","0.0","Load on","--","0","25","Line Mode"]},{"realtime":true,"field":["3b8f13a72f2f5eef18bf6dfd48875ca4","2023-08-24 05:46:59","92932010100438","232.7","50.3","133.7","0.7","0","0","0","232.7","50.3","266","266","4","Grid Tie","00075.04","230.0","23.9","48.0","230.0","23.9","50.0","5500","5500","46.0","56.4","54.0","USER","40","60","UPS","SUB","CSO","9","54.0","365","0","0.0","Load on","--","0","28","Line Mode"]},{"realtime":true,"field":["2d39923c6a1507f6577bd10a228736cb","2023-08-24 05:52:04","92932010100438","231.8","50.0","130.0","0.7","0","0","0","231.8","50.0","264","264","4","Grid Tie","00075.04","230.0","23.9","48.0","230.0","23.9","50.0","5500","5500","46.0","56.4","54.0","USER","40","60","UPS","SUB","CSO","9","54.0","364","0","0.0","Load on","--","0","32","Line Mode"]},{"realtime":true,"field":["063b873ae613366476cf464916e2d691","2023-08-24 05:57:11","92932010100438","230.3","50.0","124.3","0.9","0","0","0","230.3","50.0","184","172","3","Grid Tie","00075.04","230.0","23.9","48.0","230.0","23.9","50.0","5500","5500","46.0","56.4","54.0","USER","40","60","UPS","SUB","CSO","9","54.0","362","0","0.0","Load on","--","0","36","Line Mode"]},{"realtime":true,"field":["288cf390bc2b945069c56d4d3b894374","2023-08-24 06:02:08","92932010100438","234.8","50.3","255.9","0.8","0","0","0","234.8","50.3","211","200","3","Grid Tie","00075.04","230.0","23.9","48.0","230.0","23.9","50.0","5500","5500","46.0","56.4","54.0","USER","40","60","UPS","SUB","CSO","9","54.0","368","0","0.0","Load on","--","0","82","Line Mode"]},{"realtime":true,"field":["1717a400c27ac22a4c24fcc105ac00f5","2023-08-24 06:07:08","92932010100438","234.5","50.2","192.9","0.8","0","0","0","234.5","50.2","211","197","3","Grid Tie","00075.04","230.0","23.9","48.0","230.0","23.9","50.0","5500","5500","46.0","56.4","54.0","USER","40","60","UPS","SUB","CSO","9","54.0","369","0","0.0","Load on","--","0","81","Line Mode"]},{"realtime":true,"field":["5dd8bc8f10d8ba544cea2e3900205551","2023-08-24 06:13:05","92932010100438","232.8","50.0","225.9","0.9","0","0","0","232.8","50.0","209","196","3","Grid Tie","00075.04","230.0","23.9","48.0","230.0","23.9","50.0","5500","5500","46.0","56.4","54.0","USER","40","60","UPS","SUB","CSO","9","54.0","365","0","0.0","Load on","--","0","113","Line Mode"]},{"realtime":true,"field":["6d2141b4025dd40466351a58a32b0772","2023-08-24 06:18:45","92932010100438","233.1","50.0","270.0","0.9","0","0","0","233.1","50.0","209","198","3","Grid Tie","00075.04","230.0","23.9","48.0","230.0","23.9","50.0","5500","5500","46.0","56.4","54.0","USER","40","60","UPS","SUB","CSO","9","54.0","369","0","0.0","Load on","--","0","156","Line Mode"]},{"realtime":true,"field":["65fa5c9a6cca6f0d5df2e2e3700ca4de","2023-08-24 06:24:34","92932010100438","233.7","50.0","208.0","0.9","0","0","0","233.7","50.0","210","198","3","Grid Tie","00075.04","230.0","23.9","48.0","230.0","23.9","50.0","5500","5500","46.0","56.4","54.0","USER","40","60","UPS","SUB","CSO","9","54.0","383","0","0.0","Load on","--","0","150","Line Mode"]},{"realtime":true,"field":["650ff26df84ba96822283467ce943dec","2023-08-24 06:30:22","92932010100438","234.3","50.0","172.3","0.9","0","0","0","234.3","50.0","210","198","3","Grid Tie","00075.04","230.0","23.9","48.0","230.0","23.9","50.0","5500","5500","46.0","56.4","54.0","USER","40","60","UPS","SUB","CSO","9","54.0","376","0","0.0","Load on","--","0","145","Line Mode"]},{"realtime":true,"field":["70c4141c1a514ef6038c11ea2fe611d6","2023-08-24 06:35:58","92932010100438","234.7","50.2","274.4","0.9","0","0","0","234.7","50.2","281","279","5","Grid Tie","00075.04","230.0","23.9","48.0","230.0","23.9","50.0","5500","5500","46.0","56.4","54.0","USER","40","60","UPS","SUB","CSO","9","54.0","368","0","0.0","Load on","--","0","234","Line Mode"]},{"realtime":true,"field":["777885046e249ffd5cadf13af0d9dd92","2023-08-24 06:41:41","92932010100438","235.1","50.3","189.1","0.9","0","0","0","235.1","50.3","290","290","5","Grid Tie","00075.04","230.0","23.9","48.0","230.0","23.9","50.0","5500","5500","46.0","56.4","54.0","USER","40","60","UPS","SUB","CSO","9","54.0","369","1","0.0","Load on","--","0","215","Line Mode"]},{"realtime":true,"field":["34dbcf63e13612dd2dbffe92e26db166","2023-08-24 06:47:12","92932010100438","233.4","50.2","152.1","1.0","0","0","0","233.4","50.2","280","273","5","Grid Tie","00075.04","230.0","23.9","48.0","230.0","23.9","50.0","5500","5500","46.0","56.4","54.0","USER","40","60","UPS","SUB","CSO","9","54.0","366","1","0.0","Load on","--","0","202","Line Mode"]},{"realtime":true,"field":["27f9af057aee3f4e45a6bab91f309a14","2023-08-24 06:52:30","92932010100438","234.7","49.9","153.3","1.0","0","0","0","234.7","49.9","281","277","5","Grid Tie","00075.04","230.0","23.9","48.0","230.0","23.9","50.0","5500","5500","46.0","56.4","54.0","USER","40","60","UPS","SUB","CSO","9","54.0","369","1","0.0","Load on","--","0","218","Line Mode"]},{"realtime":true,"field":["4b5263a7508d7ad10b5ede03a6837585","2023-08-24 06:57:40","92932010100438","235.6","50.1","154.0","1.0","0","0","0","235.6","50.1","282","279","5","Grid Tie","00075.04","230.0","23.9","48.0","230.0","23.9","50.0","5500","5500","46.0","56.4","54.0","USER","40","60","UPS","SUB","CSO","9","54.0","384","1","0.0","Load on","--","0","225","Line Mode"]},{"realtime":true,"field":["7bb9cd75e0c6e7bb387e6f787e98048a","2023-08-24 07:02:49","92932010100438","237.1","50.4","159.0","1.0","0","0","0","237.1","50.4","379","367","6","Grid Tie","00075.04","230.0","23.9","48.0","230.0","23.9","50.0","5500","5500","46.0","56.4","54.0","USER","40","60","UPS","SUB","CSO","9","54.0","372","1","0.0","Load on","--","0","244","Line Mode"]},{"realtime":true,"field":["3fc0c6bfd1a804536a793f4f28b9099d","2023-08-24 07:07:58","92932010100438","237.4","50.3","134.6","1.0","0","0","0","237.4","50.3","342","342","6","Grid Tie","00075.04","230.0","23.9","48.0","230.0","23.9","50.0","5500","5500","46.0","56.4","54.0","USER","40","60","UPS","SUB","CSO","9","54.0","372","1","0.0","Load on","--","0","230","Line Mode"]},{"realtime":true,"field":["01caa7f7506c2f140bcaa47715734ef7","2023-08-24 07:13:11","92932010100438","236.7","50.0","140.3","1.1","0","0","0","236.7","50.0","339","339","6","Grid Tie","00075.04","230.0","23.9","48.0","230.0","23.9","50.0","5500","5500","46.0","56.4","54.0","USER","40","60","UPS","SUB","CSO","9","54.0","371","1","0.0","Load on","--","0","251","Line Mode"]},{"realtime":true,"field":["21fc08bcfdcc42097288669483c3ab4f","2023-08-24 07:18:20","92932010100438","236.2","49.9","305.0","1.0","0","0","0","236.2","49.9","341","341","6","Grid Tie","00075.04","230.0","23.9","48.0","230.0","23.9","50.0","5500","5500","46.0","56.4","54.0","USER","40","60","UPS","SUB","CSO","9","54.0","391","1","0.0","Load on","--","0","344","Line Mode"]},{"realtime":true,"field":["574fed65b80a9a4e4c1c5bdbe2549adf","2023-08-24 07:23:44","92932010100438","238.1","50.0","307.1","1.0","0","0","0","238.1","50.0","340","340","6","Grid Tie","00075.04","230.0","23.9","48.0","230.0","23.9","50.0","5500","5500","46.0","56.4","54.0","USER","40","60","UPS","SUB","CSO","9","54.0","394","1","0.0","Load on","--","0","349","Line Mode"]},{"realtime":true,"field":["21261173a7ace62621fac81016e10e80","2023-08-24 07:28:54","92932010100438","239.3","50.1","308.3","1.2","0","0","0","239.3","50.1","343","343","6","Grid Tie","00075.04","230.0","23.9","48.0","230.0","23.9","50.0","5500","5500","46.0","56.4","54.0","USER","40","60","UPS","SUB","CSO","9","54.0","395","1","0.0","Load on","--","0","358","Line Mode"]},{"realtime":true,"field":["650f291d5ed1a8266afadd8bf7f3fb49","2023-08-24 07:34:21","92932010100438","240.6","50.3","319.0","1.0","0","0","0","240.6","50.3","345","345","6","Grid Tie","00075.04","230.0","23.9","48.0","230.0","23.9","50.0","5500","5500","46.0","56.4","54.0","USER","40","60","UPS","SUB","CSO","9","54.0","394","1","0.0","Load on","--","0","352","Line Mode"]},{"realtime":true,"field":["7c82b830185822ba2eab77d90668b442","2023-08-24 07:39:51","92932010100438","242.5","50.4","311.7","1.1","0","0","0","242.5","50.4","350","350","6","Grid Tie","00075.04","230.0","23.9","48.0","230.0","23.9","50.0","5500","5500","46.0","56.4","54.0","USER","40","60","UPS","SUB","CSO","9","54.0","403","1","0.0","Load on","--","0","372","Line Mode"]},{"realtime":true,"field":["2bb1d14a633d10be215ae76bcddecded","2023-08-24 07:45:29","92932010100438","238.8","50.3","321.8","1.1","0","0","0","238.8","50.3","343","343","6","Grid Tie","00075.04","230.0","23.9","48.0","230.0","23.9","50.0","5500","5500","46.0","56.4","54.0","USER","40","60","UPS","SUB","CSO","9","54.0","391","1","0.0","Load on","--","0","375","Line Mode"]},{"realtime":true,"field":["543c37ec56fa238230bb9e696e2d0975","2023-08-24 07:50:35","92932010100438","240.3","50.2","321.5","1.0","0","0","0","240.3","50.2","346","346","6","Grid Tie","00075.04","230.0","23.9","48.0","230.0","23.9","50.0","5500","5500","46.0","56.4","54.0","USER","40","60","UPS","SUB","CSO","9","54.0","391","1","0.0","Load on","--","0","361","Line Mode"]},{"realtime":true,"field":["1b97bc48a0ca2a2c792d03ede4ce24f6","2023-08-24 07:56:26","92932010100438","241.2","49.9","320.3","1.1","0","0","0","241.2","49.9","344","344","6","Grid Tie","00075.04","230.0","23.9","48.0","230.0","23.9","50.0","5500","5500","46.0","56.4","54.0","USER","40","60","UPS","SUB","CSO","9","54.0","403","1","0.0","Load on","--","0","366","Line Mode"]},{"realtime":true,"field":["3bfc99a8c1ac909e599e0935a273a094","2023-08-24 08:01:39","92932010100438","238.2","49.6","320.8","1.2","0","0","0","238.2","49.6","335","335","6","Grid Tie","00075.04","230.0","23.9","48.0","230.0","23.9","50.0","5500","5500","46.0","56.4","54.0","USER","40","60","UPS","SUB","CSO","9","54.0","392","1","0.0","Load on","--","0","367","Line Mode"]},{"realtime":true,"field":["42bb687c976292a60f431eb1688d2424","2023-08-24 08:06:58","92932010100438","240.0","50.2","322.8","1.0","0","0","0","240.0","50.2","148","148","2","Grid Tie","00075.04","230.0","23.9","48.0","230.0","23.9","50.0","5500","5500","46.0","56.4","54.0","USER","40","60","UPS","SUB","CSO","9","54.0","399","0","0.0","Load on","--","0","118","Line Mode"]},{"realtime":true,"field":["55b47e474795c4cd50b2439478aee8e4","2023-08-24 08:12:44","92932010100438","238.9","50.1","323.6","1.1","0","0","0","238.9","50.1","148","148","2","Grid Tie","00075.04","230.0","23.9","48.0","230.0","23.9","50.0","5500","5500","46.0","56.4","54.0","USER","40","60","UPS","SUB","CSO","9","54.0","394","0","0.0","Load on","--","0","117","Line Mode"]},{"realtime":true,"field":["140d15798945aaed0a6d41982e7e231c","2023-08-24 08:17:42","92932010100438","238.7","50.1","323.7","1.1","0","0","0","238.7","50.1","262","259","4","Grid Tie","00075.04","230.0","23.9","48.0","230.0","23.9","50.0","5500","5500","46.0","56.4","54.0","USER","40","60","UPS","SUB","CSO","9","54.0","397","0","0.0","Load on","--","0","255","Line Mode"]},{"realtime":true,"field":["7d8c130a305969fe7a35feb417c29654","2023-08-24 08:23:16","92932010100438","238.0","50.1","318.4","1.1","0","0","0","238.0","50.1","595","532","10","Grid Tie","00075.04","230.0","23.9","48.0","230.0","23.9","50.0","5500","5500","46.0","56.4","54.0","USER","40","60","UPS","SUB","CSO","9","54.0","393","1","0.0","Load on","--","0","597","Line Mode"]},{"realtime":true,"field":["59970b335e26fa2d11ea19f636313622","2023-08-24 08:28:26","92932010100438","238.3","49.9","321.2","1.1","0","0","0","238.3","49.9","595","542","10","Grid Tie","00075.04","230.0","23.9","48.0","230.0","23.9","50.0","5500","5500","46.0","56.4","54.0","USER","40","60","UPS","SUB","CSO","9","54.0","393","1","0.0","Load on","--","0","598","Line Mode"]},{"realtime":true,"field":["2d2fb47441cdf47d028f771e4b44967e","2023-08-24 08:33:51","92932010100438","241.4","50.3","321.1","1.1","0","0","0","241.4","50.3","603","554","10","Grid Tie","00075.04","230.0","23.9","48.0","230.0","23.9","50.0","5500","5500","46.0","56.4","54.0","USER","40","60","UPS","SUB","CSO","9","54.0","398","1","0.0","Load on","--","0","615","Line Mode"]},{"realtime":true,"field":["57b3110239d3f9f96e64a836d6482d06","2023-08-24 08:39:10","92932010100438","240.2","50.2","316.9","1.2","0","0","0","240.2","50.2","601","547","10","Grid Tie","00075.04","230.0","23.9","48.0","230.0","23.9","50.0","5500","5500","46.0","56.4","54.0","USER","40","60","UPS","SUB","CSO","9","54.0","396","1","0.0","Load on","--","0","612","Line Mode"]},{"realtime":true,"field":["47d2f185b6187cec6b8d4dc0cbfc2a12","2023-08-24 08:44:18","92932010100438","240.8","50.2","318.0","1.2","0","0","0","240.8","50.2","577","538","10","Grid Tie","00075.04","230.0","23.9","48.0","230.0","23.9","50.0","5500","5500","46.0","56.4","54.0","USER","40","60","UPS","SUB","CSO","9","54.0","397","1","0.0","Load on","--","0","611","Line Mode"]},{"realtime":true,"field":["0b3b92a91bc888b767f712d3f465b558","2023-08-24 08:50:03","92932010100438","240.8","49.9","321.1","1.2","0","0","0","240.8","49.9","577","531","10","Grid Tie","00075.04","230.0","23.9","48.0","230.0","23.9","50.0","5500","5500","46.0","56.4","54.0","USER","40","60","UPS","SUB","CSO","9","54.0","397","1","0.0","Load on","--","0","608","Line Mode"]},{"realtime":true,"field":["478696ba05624f4228a1fbb621eeb5bd","2023-08-24 08:55:17","92932010100438","239.4","49.8","318.7","1.2","0","0","0","239.4","49.8","574","516","10","Grid Tie","00075.04","230.0","23.9","48.0","230.0","23.9","50.0","5500","5500","46.0","56.4","54.0","USER","40","60","UPS","SUB","CSO","9","54.0","395","1","0.0","Load on","--","0","581","Line Mode"]},{"realtime":true,"field":["4b3e3281805872916ad0c0739f5c8552","2023-08-24 09:00:16","92932010100438","239.5","49.8","321.2","1.2","0","0","0","239.5","49.8","574","515","10","Grid Tie","00075.04","230.0","23.9","48.0","230.0","23.9","50.0","5500","5500","46.0","56.4","54.0","USER","40","60","UPS","SUB","CSO","9","54.0","395","1","0.0","Load on","--","0","574","Line Mode"]},{"realtime":true,"field":["4fbe18def434232c5f6a64f117021014","2023-08-24 09:05:18","92932010100438","242.6","49.8","314.4","1.2","0","0","0","242.6","49.8","582","521","10","Grid Tie","00075.04","230.0","23.9","48.0","230.0","23.9","50.0","5500","5500","46.0","56.4","54.0","USER","40","60","UPS","SUB","CSO","9","54.0","399","1","0.0","Load on","--","0","595","Line Mode"]},{"realtime":true,"field":["17f40dea3eebb6aa498f6464d9ab3bbd","2023-08-24 09:10:34","92932010100438","243.0","50.2","321.8","1.4","0","0","0","243.0","50.2","583","522","10","Grid Tie","00075.04","230.0","23.9","48.0","230.0","23.9","50.0","5500","5500","46.0","56.4","54.0","USER","40","60","UPS","SUB","CSO","9","54.0","400","1","0.0","Load on","--","0","597","Line Mode"]},{"realtime":true,"field":["2a7166c6294fc4c226e98c3a12d9456b","2023-08-24 09:15:32","92932010100438","242.7","50.3","320.6","1.3","0","0","0","242.7","50.3","557","517","10","Grid Tie","00075.04","230.0","23.9","48.0","230.0","23.9","50.0","5500","5500","46.0","56.4","54.0","USER","40","60","UPS","SUB","CSO","9","54.0","400","1","0.0","Load on","--","0","604","Line Mode"]},{"realtime":true,"field":["163b7b4fbfad1494730aadbb57af618e","2023-08-24 09:20:51","92932010100438","242.5","50.4","318.4","1.2","0","0","0","242.5","50.4","654","604","11","Grid Tie","00075.04","230.0","23.9","48.0","230.0","23.9","50.0","5500","5500","46.0","56.4","54.0","USER","40","60","UPS","SUB","CSO","9","54.0","400","2","0.0","Load on","--","0","689","Line Mode"]},{"realtime":true,"field":["2b8f0838241b194265ca7aeb977d0706","2023-08-24 09:25:50","92932010100438","240.8","49.9","317.4","1.3","0","0","0","240.8","49.9","698","673","12","Grid Tie","00075.04","230.0","23.9","48.0","230.0","23.9","50.0","5500","5500","46.0","56.4","54.0","USER","40","60","UPS","SUB","CSO","9","54.0","397","2","0.0","Load on","--","0","754","Line Mode"]},{"realtime":true,"field":["07c63fbd3b1894ca6de215fe0988cc9b","2023-08-24 09:31:06","92932010100438","242.6","50.0","317.1","1.2","0","0","0","242.6","50.0","703","677","12","Grid Tie","00075.04","230.0","23.9","48.0","230.0","23.9","50.0","5500","5500","46.0","56.4","54.0","USER","40","60","UPS","SUB","CSO","9","54.0","400","2","0.0","Load on","--","0","760","Line Mode"]},{"realtime":true,"field":["09190b53c1da3c1f3492a39261d33405","2023-08-24 09:36:33","92932010100438","241.3","50.0","312.5","1.3","0","0","0","241.3","50.0","699","669","12","Grid Tie","00075.04","230.0","23.9","48.0","230.0","23.9","50.0","5500","5500","46.0","56.4","54.0","USER","40","60","UPS","SUB","CSO","9","54.0","398","2","0.0","Load on","--","0","751","Line Mode"]},{"realtime":true,"field":["5bc260cbf31161bf5506e556a66d6ba4","2023-08-24 09:41:36","92932010100438","240.0","49.6","311.1","1.2","0","0","0","240.0","49.6","696","664","12","Grid Tie","00075.04","230.0","23.9","48.0","230.0","23.9","50.0","5500","5500","46.0","56.4","54.0","USER","40","60","UPS","SUB","CSO","9","54.0","396","2","0.0","Load on","--","0","739","Line Mode"]},{"realtime":true,"field":["3368588a46989b036a466bc82919724c","2023-08-24 09:46:37","92932010100438","240.6","50.0","320.5","1.3","0","0","0","240.6","50.0","698","670","12","Grid Tie","00075.04","230.0","23.9","48.0","230.0","23.9","50.0","5500","5500","46.0","56.4","54.0","USER","40","60","UPS","SUB","CSO","9","54.0","397","2","0.0","Load on","--","0","742","Line Mode"]},{"realtime":true,"field":["652464ef4b20b81d1bcb359a9d3221df","2023-08-24 09:52:09","92932010100438","240.4","50.1","320.2","1.3","0","0","0","240.4","50.1","697","664","12","Grid Tie","00075.04","230.0","23.9","48.0","230.0","23.9","50.0","5500","5500","46.0","56.4","54.0","USER","40","60","UPS","SUB","CSO","9","54.0","396","2","0.0","Load on","--","0","742","Line Mode"]},{"realtime":true,"field":["2e80f0d5b4967b2453f7a388f96237e3","2023-08-24 09:57:15","92932010100438","240.7","50.0","317.8","1.3","0","0","0","240.7","50.0","698","673","12","Grid Tie","00075.04","230.0","23.9","48.0","230.0","23.9","50.0","5500","5500","46.0","56.4","54.0","USER","40","60","UPS","SUB","CSO","9","54.0","397","2","0.0","Load on","--","0","777","Line Mode"]},{"realtime":true,"field":["1417868d1679d0c6450cb73b5eefe228","2023-08-24 10:02:35","92932010100438","238.8","50.1","317.1","1.3","0","0","0","238.8","50.1","692","671","12","Grid Tie","00075.04","230.0","23.9","48.0","230.0","23.9","50.0","5500","5500","46.0","56.4","54.0","USER","40","60","UPS","SUB","CSO","9","54.0","394","2","0.0","Load on","--","0","768","Line Mode"]},{"realtime":true,"field":["655f71b6125231390e34a61e53fea259","2023-08-24 10:08:01","92932010100438","237.5","50.2","316.2","1.3","0","0","0","237.5","50.2","712","689","12","Grid Tie","00075.04","230.0","23.9","48.0","230.0","23.9","50.0","5500","5500","46.0","56.4","54.0","USER","40","60","UPS","SUB","CSO","9","54.0","392","2","0.0","Load on","--","0","788","Line Mode"]},{"realtime":true,"field":["43ad75000b9d2f782f9caa1a2d1d9a13","2023-08-24 10:13:20","92932010100438","237.4","50.3","317.8","1.3","0","0","0","237.4","50.3","593","535","10","Grid Tie","00075.04","230.0","23.9","48.0","230.0","23.9","50.0","5500","5500","46.0","56.4","54.0","USER","40","60","UPS","SUB","CSO","9","54.0","392","1","0.0","Load on","--","0","617","Line Mode"]},{"realtime":true,"field":["0756f298b020a9f2073c65f371fd88cc","2023-08-24 10:16:10","92932010100438","237.5","50.2","317.8","1.4","0","0","0","237.5","50.2","570","518","10","Grid Tie","00075.04","230.0","23.9","48.0","230.0","23.9","50.0","5500","5500","46.0","56.4","54.0","USER","40","60","UPS","SUB","CSO","9","54.0","393","1","0.0","Load on","--","0","597","Line Mode"]},{"realtime":true,"field":["6ba904f336a93916503904947b1e1163","2023-08-24 10:21:29","92932010100438","238.3","50.0","318.3","1.3","0","0","0","238.3","50.0","572","533","10","Grid Tie","00075.04","230.0","23.9","48.0","230.0","23.9","50.0","5500","5500","46.0","56.4","54.0","USER","40","60","UPS","SUB","CSO","9","54.0","393","1","0.0","Load on","--","0","615","Line Mode"]},{"realtime":true,"field":["3f0e9c0cdbb37a1e2a68382e94fe7a7d","2023-08-24 10:26:50","92932010100438","238.0","50.0","317.5","1.3","0","0","0","238.0","50.0","595","553","10","Grid Tie","00075.04","230.0","23.9","48.0","230.0","23.9","50.0","5500","5500","46.0","56.4","54.0","USER","40","60","UPS","SUB","CSO","9","54.0","393","2","0.0","Load on","--","0","642","Line Mode"]},{"realtime":true,"field":["18565065de88a928662ef66cfcc0c2ce","2023-08-24 10:31:50","92932010100438","238.5","50.1","318.0","1.3","0","0","0","238.5","50.1","572","524","10","Grid Tie","00075.04","230.0","23.9","48.0","230.0","23.9","50.0","5500","5500","46.0","56.4","54.0","USER","40","60","UPS","SUB","CSO","9","54.0","393","1","0.0","Load on","--","0","617","Line Mode"]},{"realtime":true,"field":["6a2782c1aa4d3da55c86a0f745986038","2023-08-24 10:36:52","92932010100438","238.0","50.1","317.7","1.3","0","0","0","238.0","50.1","571","526","10","Grid Tie","00075.04","230.0","23.9","48.0","230.0","23.9","50.0","5500","5500","46.0","56.4","54.0","USER","40","60","UPS","SUB","CSO","9","54.0","393","1","0.0","Load on","--","0","612","Line Mode"]},{"realtime":true,"field":["10c8852f6cd0acde613a7b05dafa6d18","2023-08-24 10:42:00","92932010100438","237.1","50.1","318.4","1.3","0","0","0","237.1","50.1","569","525","10","Grid Tie","00075.04","230.0","23.9","48.0","230.0","23.9","50.0","5500","5500","46.0","56.4","54.0","USER","40","60","UPS","SUB","CSO","9","54.0","392","1","0.0","Load on","--","0","611","Line Mode"]},{"realtime":true,"field":["69f216cd1d27e37006ebeb430fdc0b33","2023-08-24 10:46:58","92932010100438","236.2","50.0","317.5","1.3","0","0","0","236.2","50.0","567","528","10","Grid Tie","00075.04","230.0","23.9","48.0","230.0","23.9","50.0","5500","5500","46.0","56.4","54.0","USER","40","60","UPS","SUB","CSO","9","54.0","390","1","0.0","Load on","--","0","607","Line Mode"]},{"realtime":true,"field":["47942dd0eb5eca48426358d88444a805","2023-08-24 10:52:08","92932010100438","233.8","49.9","316.2","1.3","0","0","0","233.8","49.9","584","534","10","Grid Tie","00075.04","230.0","23.9","48.0","230.0","23.9","50.0","5500","5500","46.0","56.4","54.0","USER","40","60","UPS","SUB","CSO","9","54.0","387","1","0.0","Load on","--","0","605","Line Mode"]},{"realtime":true,"field":["1b7be509a388c5a662545647f6cae8c6","2023-08-24 10:57:06","92932010100438","232.2","50.0","315.3","1.3","0","0","0","232.2","50.0","580","545","10","Grid Tie","00075.04","230.0","23.9","48.0","230.0","23.9","50.0","5500","5500","46.0","56.4","54.0","USER","40","60","UPS","SUB","CSO","9","54.0","384","1","0.0","Load on","--","0","616","Line Mode"]},{"realtime":true,"field":["73df2feb533af0fa0bd96d30bd70d995","2023-08-24 11:03:16","92932010100438","232.2","49.8","309.0","1.2","0","0","0","232.2","49.8","580","546","10","Grid Tie","00075.04","230.0","23.9","48.0","230.0","23.9","50.0","5500","5500","46.0","56.4","54.0","USER","40","60","UPS","SUB","CSO","9","54.0","384","2","0.0","Load on","--","0","624","Line Mode"]},{"realtime":true,"field":["546326d670f22afe46c4372344e9b4e0","2023-08-24 11:08:27","92932010100438","233.1","50.0","317.4","1.3","0","0","0","233.1","50.0","652","617","11","Grid Tie","00075.04","230.0","23.9","48.0","230.0","23.9","50.0","5500","5500","46.0","56.4","54.0","USER","40","60","UPS","SUB","CSO","9","54.0","386","2","0.0","Load on","--","0","694","Line Mode"]},{"realtime":true,"field":["48b022fc4b8fc1526e7bf3d88776168c","2023-08-24 11:14:19","92932010100438","233.0","49.9","313.1","1.4","0","0","0","233.0","49.9","605","557","11","Grid Tie","00075.04","230.0","23.9","48.0","230.0","23.9","50.0","5500","5500","46.0","56.4","54.0","USER","40","60","UPS","SUB","CSO","9","54.0","386","1","0.0","Load on","--","0","620","Line Mode"]},{"realtime":true,"field":["4a18dffda725edf35d46bfb9a7be158d","2023-08-24 11:19:50","92932010100438","233.0","49.9","321.7","1.3","0","0","0","233.0","49.9","605","553","11","Grid Tie","00075.04","230.0","23.9","48.0","230.0","23.9","50.0","5500","5500","46.0","56.4","54.0","USER","40","60","UPS","SUB","CSO","9","54.0","386","1","0.0","Load on","--","0","620","Line Mode"]},{"realtime":true,"field":["67552200a5ad75ba0a3a3000f8afab87","2023-08-24 11:25:57","92932010100438","233.3","50.1","304.6","1.3","0","0","0","233.3","50.1","629","576","11","Grid Tie","00075.04","230.0","23.9","48.0","230.0","23.9","50.0","5500","5500","46.0","56.4","54.0","USER","40","60","UPS","SUB","CSO","9","54.0","386","2","0.0","Load on","--","0","657","Line Mode"]},{"realtime":true,"field":["66b2b2b4270d8560635f533980f5c6a0","2023-08-24 11:31:00","92932010100438","231.8","50.2","318.1","1.3","0","0","0","231.8","50.2","602","567","10","Grid Tie","00075.04","230.0","23.9","48.0","230.0","23.9","50.0","5500","5500","46.0","56.4","54.0","USER","40","60","UPS","SUB","CSO","9","54.0","384","2","0.0","Load on","--","0","638","Line Mode"]},{"realtime":true,"field":["71b7f130c251889104c4a58efd2fb02f","2023-08-24 11:37:00","92932010100438","231.6","50.3","314.6","1.4","0","0","0","231.6","50.3","625","572","11","Grid Tie","00075.04","230.0","23.9","48.0","230.0","23.9","50.0","5500","5500","46.0","56.4","54.0","USER","40","60","UPS","SUB","CSO","9","54.0","384","2","0.0","Load on","--","0","650","Line Mode"]},{"realtime":true,"field":["6d4d87968b01e5013404082886774237","2023-08-24 11:42:10","92932010100438","233.2","50.4","298.7","1.3","0","0","0","233.2","50.4","629","579","11","Grid Tie","00075.04","230.0","23.9","48.0","230.0","23.9","50.0","5500","5500","46.0","56.4","54.0","USER","40","60","UPS","SUB","CSO","9","54.0","386","2","0.0","Load on","--","0","667","Line Mode"]},{"realtime":true,"field":["3b799827033d99cb23f0d2111c168b8f","2023-08-24 11:47:51","92932010100438","233.3","50.5","306.9","1.3","0","0","0","233.3","50.5","606","558","11","Grid Tie","00075.04","230.0","23.9","48.0","230.0","23.9","50.0","5500","5500","46.0","56.4","54.0","USER","40","60","UPS","SUB","CSO","9","54.0","386","2","0.0","Load on","--","0","636","Line Mode"]},{"realtime":true,"field":["51e73acd0e3a372a56cfe6ac8ad2d313","2023-08-24 11:52:52","92932010100438","230.7","50.1","309.6","1.3","0","0","0","230.7","50.1","622","573","11","Grid Tie","00075.04","230.0","23.9","48.0","230.0","23.9","50.0","5500","5500","46.0","56.4","54.0","USER","40","60","UPS","SUB","CSO","9","54.0","382","2","0.0","Load on","--","0","642","Line Mode"]},{"realtime":true,"field":["053d9f110a3c774e57d8febd34252577","2023-08-24 11:58:35","92932010100438","230.8","49.9","319.0","1.3","0","0","0","230.8","49.9","600","555","10","Grid Tie","00075.04","230.0","23.9","48.0","230.0","23.9","50.0","5500","5500","46.0","56.4","54.0","USER","40","60","UPS","SUB","CSO","9","54.0","382","1","0.0","Load on","--","0","626","Line Mode"]},{"realtime":true,"field":["22301a9904cb34e7374a0b869b6bf0f1","2023-08-24 12:04:53","92932010100438","237.7","50.4","300.8","1.3","0","0","0","237.7","50.4","1711","1707","31","Grid Tie","00075.04","230.0","23.9","48.0","230.0","23.9","50.0","5500","5500","46.0","56.4","54.0","USER","40","60","UPS","SUB","CSO","9","54.0","393","6","0.0","Load on","--","0","1908","Line Mode"]},{"realtime":true,"field":["2c075c125904369721bafd2390e484e6","2023-08-24 12:10:39","92932010100438","238.5","49.9","305.5","1.3","0","0","0","238.5","49.9","500","457","9","Grid Tie","00075.04","230.0","23.9","48.0","230.0","23.9","50.0","5500","5500","46.0","56.4","54.0","USER","40","60","UPS","SUB","CSO","9","54.0","394","1","0.0","Load on","--","0","533","Line Mode"]},{"realtime":true,"field":["48ca60d39359548b6ee715ce866a443a","2023-08-24 12:16:25","92932010100438","237.7","49.9","310.6","1.3","0","0","0","237.7","49.9","499","465","9","Grid Tie","00075.04","230.0","23.9","48.0","230.0","23.9","50.0","5500","5500","46.0","56.4","54.0","USER","40","60","UPS","SUB","CSO","9","54.0","392","1","0.0","Load on","--","0","548","Line Mode"]},{"realtime":true,"field":["542fb669e8923e741704999925bb03bd","2023-08-24 12:22:25","92932010100438","237.6","49.8","305.6","1.3","0","0","0","237.6","49.8","1671","1671","30","Grid Tie","00075.04","230.0","23.9","48.0","230.0","23.9","50.0","5500","5500","46.0","56.4","54.0","USER","40","60","UPS","SUB","CSO","9","54.0","392","6","0.0","Load on","--","0","1865","Line Mode"]},{"realtime":true,"field":["32747c6ccfa63f177e9f8b77feb05204","2023-08-24 12:28:42","92932010100438","238.0","49.9","312.2","1.2","0","0","0","238.0","49.9","499","461","9","Grid Tie","00075.04","230.0","23.9","48.0","230.0","23.9","50.0","5500","5500","46.0","56.4","54.0","USER","40","60","UPS","SUB","CSO","9","54.0","392","1","0.0","Load on","--","0","534","Line Mode"]},{"realtime":true,"field":["34ad844c01cdaf155d4f634cd330c124","2023-08-24 12:34:33","92932010100438","236.9","49.7","315.0","1.3","0","0","0","236.9","49.7","497","458","9","Grid Tie","00075.04","230.0","23.9","48.0","230.0","23.9","50.0","5500","5500","46.0","56.4","54.0","USER","40","60","UPS","SUB","CSO","9","54.0","391","1","0.0","Load on","--","0","524","Line Mode"]},{"realtime":true,"field":["6a40a2e791493a542c8241b6c4766d22","2023-08-24 12:40:43","92932010100438","236.7","50.0","315.2","1.3","0","0","0","236.7","50.0","331","287","6","Grid Tie","00075.04","230.0","23.9","48.0","230.0","23.9","50.0","5500","5500","46.0","56.4","54.0","USER","40","60","UPS","SUB","CSO","9","54.0","407","0","0.0","Load on","--","0","262","Line Mode"]},{"realtime":true,"field":["715035b683f90738487f3304a1e537ca","2023-08-24 12:46:50","92932010100438","239.7","50.4","308.0","1.3","0","0","0","239.7","50.4","479","455","8","Grid Tie","00075.04","230.0","23.9","48.0","230.0","23.9","50.0","5500","5500","46.0","56.4","54.0","USER","40","60","UPS","SUB","CSO","9","54.0","395","1","0.0","Load on","--","0","546","Line Mode"]},{"realtime":true,"field":["606eba9d8d081167574c2affc3db13dd","2023-08-24 12:53:19","92932010100438","236.8","50.3","319.7","1.3","0","0","0","236.8","50.3","473","445","8","Grid Tie","00075.04","230.0","23.9","48.0","230.0","23.9","50.0","5500","5500","46.0","56.4","54.0","USER","40","60","UPS","SUB","CSO","9","54.0","391","1","0.0","Load on","--","0","505","Line Mode"]},{"realtime":true,"field":["795309907f61433c2f3efc3ed6859b18","2023-08-24 12:59:40","92932010100438","235.3","49.8","315.6","1.3","0","0","0","235.3","49.8","470","425","8","Grid Tie","00075.04","230.0","23.9","48.0","230.0","23.9","50.0","5500","5500","46.0","56.4","54.0","USER","40","60","UPS","SUB","CSO","9","54.0","389","1","0.0","Load on","--","0","495","Line Mode"]},{"realtime":true,"field":["2046991ff24b919f59ec21503ec721bb","2023-08-24 13:07:02","92932010100438","235.7","50.1","313.1","1.3","0","0","0","235.7","50.1","518","477","9","Grid Tie","00075.04","230.0","23.9","48.0","230.0","23.9","50.0","5500","5500","46.0","56.4","54.0","USER","40","60","UPS","SUB","CSO","9","54.0","390","1","0.0","Load on","--","0","547","Line Mode"]},{"realtime":true,"field":["4a08043efc8ddf5c46bc99d9aeff312c","2023-08-24 13:13:13","92932010100438","233.3","49.8","301.2","1.3","0","0","0","233.3","49.8","536","488","9","Grid Tie","00075.04","230.0","23.9","48.0","230.0","23.9","50.0","5500","5500","46.0","56.4","54.0","USER","40","60","UPS","SUB","CSO","9","54.0","387","1","0.0","Load on","--","0","543","Line Mode"]},{"realtime":true,"field":["4462e1e180d565133242eaf17f7e5ba5","2023-08-24 13:19:14","92932010100438","234.1","50.2","304.6","1.3","0","0","0","234.1","50.2","491","449","8","Grid Tie","00075.04","230.0","23.9","48.0","230.0","23.9","50.0","5500","5500","46.0","56.4","54.0","USER","40","60","UPS","SUB","CSO","9","54.0","388","1","0.0","Load on","--","0","538","Line Mode"]},{"realtime":true,"field":["0e1ba2760e66d3dd2eed8ea1cf8309dc","2023-08-24 13:25:31","92932010100438","234.9","49.9","315.6","1.4","0","0","0","234.9","49.9","493","453","8","Grid Tie","00075.04","230.0","23.9","48.0","230.0","23.9","50.0","5500","5500","46.0","56.4","54.0","USER","40","60","UPS","SUB","CSO","9","54.0","388","1","0.0","Load on","--","0","525","Line Mode"]},{"realtime":true,"field":["2ef4ef7225671e6968d817a1b8b9db2d","2023-08-24 13:31:20","92932010100438","235.8","49.9","314.4","1.3","0","0","0","235.8","49.9","589","542","10","Grid Tie","00075.04","230.0","23.9","48.0","230.0","23.9","50.0","5500","5500","46.0","56.4","54.0","USER","40","60","UPS","SUB","CSO","9","54.0","390","1","0.0","Load on","--","0","628","Line Mode"]},{"realtime":true,"field":["12eec6aeebfa0c7e230c5f0bc3d83343","2023-08-24 13:37:19","92932010100438","234.9","50.1","315.0","1.3","0","0","0","234.9","50.1","610","563","11","Grid Tie","00075.04","230.0","23.9","48.0","230.0","23.9","50.0","5500","5500","46.0","56.4","54.0","USER","40","60","UPS","SUB","CSO","9","54.0","388","2","0.0","Load on","--","0","654","Line Mode"]},{"realtime":true,"field":["7eb5ea81b7943f853faac553a527a1c1","2023-08-24 13:43:22","92932010100438","234.1","50.0","310.8","1.3","0","0","0","234.1","50.0","678","636","12","Grid Tie","00075.04","230.0","23.9","48.0","230.0","23.9","50.0","5500","5500","46.0","56.4","54.0","USER","40","60","UPS","SUB","CSO","9","54.0","387","2","0.0","Load on","--","0","735","Line Mode"]},{"realtime":true,"field":["66db0103e328d66b3eeed55f2750f7a0","2023-08-24 13:49:31","92932010100438","232.8","50.0","310.8","1.3","0","0","0","232.8","50.0","675","637","12","Grid Tie","00075.04","230.0","23.9","48.0","230.0","23.9","50.0","5500","5500","46.0","56.4","54.0","USER","40","60","UPS","SUB","CSO","9","54.0","385","2","0.0","Load on","--","0","729","Line Mode"]},{"realtime":true,"field":["4237e475ca99099609b367fbfd97707e","2023-08-24 13:55:50","92932010100438","231.8","49.7","310.3","1.3","0","0","0","231.8","49.7","649","621","11","Grid Tie","00075.04","230.0","23.9","48.0","230.0","23.9","50.0","5500","5500","46.0","56.4","54.0","USER","40","60","UPS","SUB","CSO","9","54.0","384","2","0.0","Load on","--","0","708","Line Mode"]},{"realtime":true,"field":["6911e8b99babcf417cea1bf239d39aad","2023-08-24 14:02:01","92932010100438","232.3","49.9","310.3","1.3","0","0","0","232.3","49.9","673","640","12","Grid Tie","00075.04","230.0","23.9","48.0","230.0","23.9","50.0","5500","5500","46.0","56.4","54.0","USER","40","60","UPS","SUB","CSO","9","54.0","384","2","0.0","Load on","--","0","718","Line Mode"]},{"realtime":true,"field":["350dc013341715b11640f5dfea77e16e","2023-08-24 14:07:18","92932010100438","231.5","49.9","310.6","1.3","0","0","0","231.5","49.9","601","562","10","Grid Tie","00075.04","230.0","23.9","48.0","230.0","23.9","50.0","5500","5500","46.0","56.4","54.0","USER","40","60","UPS","SUB","CSO","9","54.0","383","2","0.0","Load on","--","0","649","Line Mode"]},{"realtime":true,"field":["334058e64652252178a9c64bc82f1a2b","2023-08-24 14:14:11","92932010100438","229.2","50.1","311.8","1.3","0","0","0","229.2","50.1","595","546","10","Grid Tie","00075.04","230.0","23.9","48.0","230.0","23.9","50.0","5500","5500","46.0","56.4","54.0","USER","40","60","UPS","SUB","CSO","9","54.0","380","1","0.0","Load on","--","0","618","Line Mode"]},{"realtime":true,"field":["584d219934917acf39a75027b2a3ef82","2023-08-24 14:19:57","92932010100438","231.0","50.3","308.7","1.2","0","0","0","231.0","50.3","577","543","10","Grid Tie","00075.04","230.0","23.9","48.0","230.0","23.9","50.0","5500","5500","46.0","56.4","54.0","USER","40","60","UPS","SUB","CSO","9","54.0","383","2","0.0","Load on","--","0","625","Line Mode"]},{"realtime":true,"field":["176715226106d963571cddae90408478","2023-08-24 14:26:34","92932010100438","227.6","49.9","318.0","1.3","0","0","0","227.6","49.9","546","513","9","Grid Tie","00075.04","230.0","23.9","48.0","230.0","23.9","50.0","5500","5500","46.0","56.4","54.0","USER","40","60","UPS","SUB","CSO","9","54.0","377","1","0.0","Load on","--","0","564","Line Mode"]},{"realtime":true,"field":["26605ab3898e411609c95b272be87368","2023-08-24 14:32:22","92932010100438","229.8","49.8","255.4","1.3","0","0","0","229.8","49.8","1677","1662","30","Grid Tie","00075.04","230.0","23.9","48.0","230.0","23.9","50.0","5500","5500","46.0","56.4","54.0","USER","40","60","UPS","SUB","CSO","9","54.0","360","6","0.0","Load on","--","0","1629","Line Mode"]},{"realtime":true,"field":["39500303be6559c47d88e4ce14604495","2023-08-24 14:38:32","92932010100438","226.2","49.6","198.5","1.2","0","0","0","226.2","49.6","1606","1604","29","Grid Tie","00075.04","230.0","23.9","48.0","230.0","23.9","50.0","5500","5500","46.0","56.4","54.0","USER","40","60","UPS","SUB","CSO","9","54.0","355","4","0.0","Load on","--","0","916","Line Mode"]},{"realtime":true,"field":["2b3bf735433b5742613e1c2fcbb9f117","2023-08-24 14:44:46","92932010100438","224.1","49.8","304.0","1.3","0","0","0","224.1","49.8","425","389","7","Grid Tie","00075.04","230.0","23.9","48.0","230.0","23.9","50.0","5500","5500","46.0","56.4","54.0","USER","40","60","UPS","SUB","CSO","9","54.0","372","1","0.0","Load on","--","0","441","Line Mode"]},{"realtime":true,"field":["5c2c898cdf6c3a6f0153f496bbc461bf","2023-08-24 14:50:45","92932010100438","223.9","50.3","282.8","1.2","0","0","0","223.9","50.3","2065","2065","37","Grid Tie","00075.04","230.0","23.9","48.0","230.0","23.9","50.0","5500","5500","46.0","56.4","54.0","USER","40","60","UPS","SUB","CSO","9","54.0","372","8","0.0","Load on","--","0","2266","Line Mode"]},{"realtime":true,"field":["6963400e0f677ed40f3525f5df05ddef","2023-08-24 14:57:06","92932010100438","229.2","49.8","268.1","1.3","0","0","0","229.2","49.8","2543","2512","46","Grid Tie","00075.04","230.0","23.9","48.0","230.0","23.9","50.0","5500","5500","46.0","56.4","54.0","USER","40","60","UPS","SUB","CSO","9","54.0","360","8","0.0","Load on","--","0","2228","Line Mode"]},{"realtime":true,"field":["54cbcd76847d370b349dc9ea2bfb7c28","2023-08-24 15:02:53","92932010100438","230.4","49.7","267.6","1.2","0","0","0","230.4","49.7","2050","2050","37","Grid Tie","00075.04","230.0","23.9","48.0","230.0","23.9","50.0","5500","5500","46.0","56.4","54.0","USER","40","60","UPS","SUB","CSO","9","54.0","362","7","0.0","Load on","--","0","2113","Line Mode"]},{"realtime":true,"field":["6e49f1b9b0a132544931c2d762797ef3","2023-08-24 15:08:42","92932010100438","229.9","49.6","267.6","1.2","0","0","0","229.9","49.6","1977","1958","35","Grid Tie","00075.04","230.0","23.9","48.0","230.0","23.9","50.0","5500","5500","46.0","56.4","54.0","USER","40","60","UPS","SUB","CSO","9","54.0","361","7","0.0","Load on","--","0","2031","Line Mode"]},{"realtime":true,"field":["1df9ab270c008b3e398da162891c09a4","2023-08-24 15:14:10","92932010100438","229.5","49.9","227.8","1.2","0","0","0","229.5","49.9","1817","1817","33","Grid Tie","00075.04","230.0","23.9","48.0","230.0","23.9","50.0","5500","5500","46.0","56.4","54.0","USER","40","60","UPS","SUB","CSO","9","54.0","361","7","0.0","Load on","--","0","1791","Line Mode"]},{"realtime":true,"field":["72676dbd82201bc15bff9d4b5ad01599","2023-08-24 15:19:38","92932010100438","231.3","50.4","271.6","1.2","0","0","0","231.3","50.4","1757","1743","31","Grid Tie","00075.04","230.0","23.9","48.0","230.0","23.9","50.0","5500","5500","46.0","56.4","54.0","USER","40","60","UPS","SUB","CSO","9","54.0","382","7","0.0","Load on","--","0","1923","Line Mode"]},{"realtime":true,"field":["2d5fb5f1f3d7418f55154b7244a60d8a","2023-08-24 15:24:47","92932010100438","231.2","49.9","266.8","1.2","0","0","0","231.2","49.9","1766","1766","32","Grid Tie","00075.04","230.0","23.9","48.0","230.0","23.9","50.0","5500","5500","46.0","56.4","54.0","USER","40","60","UPS","SUB","CSO","9","54.0","363","6","0.0","Load on","--","0","1859","Line Mode"]},{"realtime":true,"field":["400f530b5c95d5b1562cbbc558d7887d","2023-08-24 15:29:53","92932010100438","229.0","49.9","269.4","1.2","0","0","0","229.0","49.9","1925","1925","35","Grid Tie","00075.04","230.0","23.9","48.0","230.0","23.9","50.0","5500","5500","46.0","56.4","54.0","USER","40","60","UPS","SUB","CSO","9","54.0","359","6","0.0","Load on","--","0","1820","Line Mode"]},{"realtime":true,"field":["3e9824a03f3ccc845bfcca63bbf62758","2023-08-24 15:34:54","92932010100438","228.7","49.6","258.5","1.4","0","0","0","228.7","49.6","2081","2059","37","Grid Tie","00075.04","230.0","23.9","48.0","230.0","23.9","50.0","5500","5500","46.0","56.4","54.0","USER","40","60","UPS","SUB","CSO","9","54.0","359","3","0.0","Load on","--","0","967","Line Mode"]},{"realtime":true,"field":["5e57651e16240fc7151d306c89423fdd","2023-08-24 15:40:05","92932010100438","230.1","49.6","270.3","1.2","0","0","0","230.1","49.6","1681","1681","30","Grid Tie","00075.04","230.0","23.9","48.0","230.0","23.9","50.0","5500","5500","46.0","56.4","54.0","USER","40","60","UPS","SUB","CSO","9","54.0","361","6","0.0","Load on","--","0","1721","Line Mode"]},{"realtime":true,"field":["29d6a8b203a9fcfa4ddc67d745e117e9","2023-08-24 15:45:25","92932010100438","230.6","49.9","271.0","1.2","0","0","0","230.6","49.9","1637","1629","29","Grid Tie","00075.04","230.0","23.9","48.0","230.0","23.9","50.0","5500","5500","46.0","56.4","54.0","USER","40","60","UPS","SUB","CSO","9","54.0","362","5","0.0","Load on","--","0","1614","Line Mode"]},{"realtime":true,"field":["14e886dd406f5d433f80b0b859aee4b3","2023-08-24 15:51:04","92932010100438","230.9","50.1","271.9","1.2","0","0","0","230.9","50.1","1708","1695","31","Grid Tie","00075.04","230.0","23.9","48.0","230.0","23.9","50.0","5500","5500","46.0","56.4","54.0","USER","40","60","UPS","SUB","CSO","9","54.0","363","5","0.0","Load on","--","0","1525","Line Mode"]},{"realtime":true,"field":["54116bd88f9edad138f7eb91ec570709","2023-08-24 15:56:49","92932010100438","231.4","50.2","268.8","1.1","0","0","0","231.4","50.2","1666","1652","30","Grid Tie","00075.04","230.0","23.9","48.0","230.0","23.9","50.0","5500","5500","46.0","56.4","54.0","USER","40","60","UPS","SUB","CSO","9","54.0","363","5","0.0","Load on","--","0","1449","Line Mode"]},{"realtime":true,"field":["1e241b4974e138890e2671d566db9c1a","2023-08-24 16:02:37","92932010100438","229.5","50.5","269.3","1.2","0","0","0","229.5","50.5","1422","1417","25","Grid Tie","00075.04","230.0","23.9","48.0","230.0","23.9","50.0","5500","5500","46.0","56.4","54.0","USER","40","60","UPS","SUB","CSO","9","54.0","361","5","0.0","Load on","--","0","1380","Line Mode"]},{"realtime":true,"field":["38cfc3526d91121f27e86a0b40abbc14","2023-08-24 16:08:22","92932010100438","227.3","49.9","256.2","1.2","0","0","0","227.3","49.9","1386","1379","25","Grid Tie","00075.04","230.0","23.9","48.0","230.0","23.9","50.0","5500","5500","46.0","56.4","54.0","USER","40","60","UPS","SUB","CSO","9","54.0","357","2","0.0","Load on","--","0","617","Line Mode"]},{"realtime":true,"field":["3116717692c8b5660133c1ea4c652b9a","2023-08-24 16:14:13","92932010100438","229.2","49.8","265.1","1.3","0","0","0","229.2","49.8","1398","1387","25","Grid Tie","00075.04","230.0","23.9","48.0","230.0","23.9","50.0","5500","5500","46.0","56.4","54.0","USER","40","60","UPS","SUB","CSO","9","54.0","360","3","0.0","Load on","--","0","915","Line Mode"]},{"realtime":true,"field":["349b3fd8e3e7563d6e6b474f5bb3e734","2023-08-24 16:20:19","92932010100438","226.0","49.8","265.7","1.3","0","0","0","226.0","49.8","1405","1405","25","Grid Tie","00075.04","230.0","23.9","48.0","230.0","23.9","50.0","5500","5500","46.0","56.4","54.0","USER","40","60","UPS","SUB","CSO","9","54.0","355","3","0.0","Load on","--","0","847","Line Mode"]},{"realtime":true,"field":["3b690ae5dfe15988200fa58a3b23a57e","2023-08-24 16:25:56","92932010100438","225.0","50.0","264.3","1.2","0","0","0","225.0","50.0","1417","1406","25","Grid Tie","00075.04","230.0","23.9","48.0","230.0","23.9","50.0","5500","5500","46.0","56.4","54.0","USER","40","60","UPS","SUB","CSO","9","54.0","354","2","0.0","Load on","--","0","675","Line Mode"]},{"realtime":true,"field":["75d64f851bd771a63f9b8ad2858f9aa7","2023-08-24 16:31:53","92932010100438","224.7","50.3","265.7","1.2","0","0","0","224.7","50.3","1415","1396","25","Grid Tie","00075.04","230.0","23.9","48.0","230.0","23.9","50.0","5500","5500","46.0","56.4","54.0","USER","40","60","UPS","SUB","CSO","9","54.0","353","2","0.0","Load on","--","0","647","Line Mode"]},{"realtime":true,"field":["0260d478d556dc8008c68d3b725baf52","2023-08-24 16:37:35","92932010100438","224.5","49.8","266.9","1.2","0","0","0","224.5","49.8","1369","1363","24","Grid Tie","00075.04","230.0","23.9","48.0","230.0","23.9","50.0","5500","5500","46.0","56.4","54.0","USER","40","60","UPS","SUB","CSO","9","54.0","353","2","0.0","Load on","--","0","758","Line Mode"]},{"realtime":true,"field":["142c1bb6f06685b5352f58555fad2a14","2023-08-24 16:43:43","92932010100438","221.2","49.8","274.4","1.1","0","0","0","221.2","49.8","1393","1383","25","Grid Tie","00075.04","230.0","23.9","48.0","230.0","23.9","50.0","5500","5500","46.0","56.4","54.0","USER","40","60","UPS","SUB","CSO","9","54.0","350","2","0.0","Load on","--","0","735","Line Mode"]},{"realtime":true,"field":["13f097902232b6fe1a9bd1d816579ca3","2023-08-24 16:49:56","92932010100438","228.2","50.2","277.1","1.2","0","0","0","228.2","50.2","1392","1387","25","Grid Tie","00075.04","230.0","23.9","48.0","230.0","23.9","50.0","5500","5500","46.0","56.4","54.0","USER","40","60","UPS","SUB","CSO","9","54.0","358","2","0.0","Load on","--","0","641","Line Mode"]},{"realtime":true,"field":["09a0a71ac06802ff17bbe0bc865a1d0d","2023-08-24 16:55:36","92932010100438","227.5","50.0","276.8","1.2","0","0","0","227.5","50.0","1411","1384","25","Grid Tie","00075.04","230.0","23.9","48.0","230.0","23.9","50.0","5500","5500","46.0","56.4","54.0","USER","40","60","UPS","SUB","CSO","9","54.0","358","2","0.0","Load on","--","0","630","Line Mode"]},{"realtime":true,"field":["7bc2b4487d57268c295fb75ede06bc12","2023-08-24 17:01:39","92932010100438","230.6","49.8","276.2","1.1","0","0","0","230.6","49.8","1383","1359","25","Grid Tie","00075.04","230.0","23.9","48.0","230.0","23.9","50.0","5500","5500","46.0","56.4","54.0","USER","40","60","UPS","SUB","CSO","9","54.0","362","2","0.0","Load on","--","0","555","Line Mode"]},{"realtime":true,"field":["447d35072063be62123c0be61462c599","2023-08-24 17:07:24","92932010100438","230.3","49.7","291.6","1.2","0","0","0","230.3","49.7","414","364","7","Grid Tie","00075.04","230.0","23.9","48.0","230.0","23.9","50.0","5500","5500","46.0","56.4","54.0","USER","40","60","UPS","SUB","CSO","9","54.0","382","1","0.0","Load on","--","0","361","Line Mode"]},{"realtime":true,"field":["257cb524f471f33b6dfb22132a082007","2023-08-24 17:13:58","92932010100438","231.5","50.0","204.5","1.2","0","0","0","231.5","50.0","416","368","7","Grid Tie","00075.04","230.0","23.9","48.0","230.0","23.9","50.0","5500","5500","46.0","56.4","54.0","USER","40","60","UPS","SUB","CSO","9","54.0","363","1","0.0","Load on","--","0","285","Line Mode"]},{"realtime":true,"field":["341822135b906dfb02a537a78870f64e","2023-08-24 17:19:29","92932010100438","230.5","50.3","265.0","1.2","0","0","0","230.5","50.3","391","365","7","Grid Tie","00075.04","230.0","23.9","48.0","230.0","23.9","50.0","5500","5500","46.0","56.4","54.0","USER","40","60","UPS","SUB","CSO","9","54.0","362","1","0.0","Load on","--","0","325","Line Mode"]},{"realtime":true,"field":["2913e671679f32287e7ec8075403f9df","2023-08-24 17:25:20","92932010100438","232.6","50.3","271.2","1.2","0","0","0","232.6","50.3","418","376","7","Grid Tie","00075.04","230.0","23.9","48.0","230.0","23.9","50.0","5500","5500","46.0","56.4","54.0","USER","40","60","UPS","SUB","CSO","9","54.0","365","1","0.0","Load on","--","0","329","Line Mode"]},{"realtime":true,"field":["4bfb255901948d2161a335482852af60","2023-08-24 17:30:53","92932010100438","236.7","50.4","260.9","1.1","0","0","0","236.7","50.4","402","369","7","Grid Tie","00075.04","230.0","23.9","48.0","230.0","23.9","50.0","5500","5500","46.0","56.4","54.0","USER","40","60","UPS","SUB","CSO","9","54.0","371","1","0.0","Load on","--","0","291","Line Mode"]},{"realtime":true,"field":["5984f766f672a1b770e423374a48c7aa","2023-08-24 17:36:30","92932010100438","237.5","50.3","259.7","1.1","0","0","0","237.5","50.3","451","402","8","Grid Tie","00075.04","230.0","23.9","48.0","230.0","23.9","50.0","5500","5500","46.0","56.4","54.0","USER","40","60","UPS","SUB","CSO","9","54.0","372","0","0.0","Load on","--","0","245","Line Mode"]},{"realtime":true,"field":["5e50473c715a67a511742ee3a07dc9fa","2023-08-24 17:41:37","92932010100438","237.2","49.9","268.4","1.1","0","0","0","237.2","49.9","450","402","8","Grid Tie","00075.04","230.0","23.9","48.0","230.0","23.9","50.0","5500","5500","46.0","56.4","54.0","USER","40","60","UPS","SUB","CSO","9","54.0","371","0","0.0","Load on","--","0","257","Line Mode"]},{"realtime":true,"field":["117334829a79f6196299e2b0c5dfcf63","2023-08-24 17:46:43","92932010100438","240.2","50.4","268.8","1.2","0","0","0","240.2","50.4","432","402","7","Grid Tie","00075.04","230.0","23.9","48.0","230.0","23.9","50.0","5500","5500","46.0","56.4","54.0","USER","40","60","UPS","SUB","CSO","9","54.0","376","1","0.0","Load on","--","0","286","Line Mode"]},{"realtime":true,"field":["7f8f46cd59572a4065499cd5890b0de2","2023-08-24 17:51:47","92932010100438","238.1","50.3","266.3","1.1","0","0","0","238.1","50.3","452","411","8","Grid Tie","00075.04","230.0","23.9","48.0","230.0","23.9","50.0","5500","5500","46.0","56.4","54.0","USER","40","60","UPS","SUB","CSO","9","54.0","373","1","0.0","Load on","--","0","287","Line Mode"]},{"realtime":true,"field":["0fc48dfcfde94c9b36f4558ec777870a","2023-08-24 17:56:50","92932010100438","237.4","50.2","264.1","1.2","0","0","0","237.4","50.2","451","419","8","Grid Tie","00075.04","230.0","23.9","48.0","230.0","23.9","50.0","5500","5500","46.0","56.4","54.0","USER","40","60","UPS","SUB","CSO","9","54.0","372","0","0.0","Load on","--","0","263","Line Mode"]},{"realtime":true,"field":["21f1aea6083f04535677b25d05183d86","2023-08-24 18:02:01","92932010100438","239.3","50.1","260.0","1.1","0","0","0","239.3","50.1","526","500","9","Grid Tie","00075.04","230.0","23.9","48.0","230.0","23.9","50.0","5500","5500","46.0","56.4","54.0","USER","40","60","UPS","SUB","CSO","9","54.0","375","0","0.0","Load on","--","0","232","Line Mode"]},{"realtime":true,"field":["478305a87708c94336a80026213f312a","2023-08-24 18:07:30","92932010100438","238.8","49.9","254.6","1.1","0","0","0","238.8","49.9","525","497","9","Grid Tie","00075.04","230.0","23.9","48.0","230.0","23.9","50.0","5500","5500","46.0","56.4","54.0","USER","40","60","UPS","SUB","CSO","9","54.0","374","0","0.0","Load on","--","0","182","Line Mode"]},{"realtime":true,"field":["46ff1286fdc3651f481cd79eaeb343d7","2023-08-24 18:13:25","92932010100438","237.9","50.0","254.0","1.1","0","0","0","237.9","50.0","523","497","9","Grid Tie","00075.04","230.0","23.9","48.0","230.0","23.9","50.0","5500","5500","46.0","56.4","54.0","USER","40","60","UPS","SUB","CSO","9","54.0","373","0","0.0","Load on","--","0","143","Line Mode"]},{"realtime":true,"field":["0eca61c58533527e0f32961ce6668eba","2023-08-24 18:19:23","92932010100438","238.1","49.9","264.0","1.1","0","0","0","238.1","49.9","452","412","8","Grid Tie","00075.04","230.0","23.9","48.0","230.0","23.9","50.0","5500","5500","46.0","56.4","54.0","USER","40","60","UPS","SUB","CSO","9","54.0","373","0","0.0","Load on","--","0","109","Line Mode"]},{"realtime":true,"field":["26b03ae76357374374527fe0c626b156","2023-08-24 18:25:07","92932010100438","240.2","49.8","252.5","1.2","0","0","0","240.2","49.8","456","413","8","Grid Tie","00075.04","230.0","23.9","48.0","230.0","23.9","50.0","5500","5500","46.0","56.4","54.0","USER","40","60","UPS","SUB","CSO","9","54.0","376","0","0.0","Load on","--","0","103","Line Mode"]},{"realtime":true,"field":["607dcbe0e79477e53a4fa5c16c085c16","2023-08-24 18:31:01","92932010100438","242.3","50.1","184.8","1.1","0","0","0","242.3","50.1","460","414","8","Grid Tie","00075.04","230.0","23.9","48.0","230.0","23.9","50.0","5500","5500","46.0","56.4","54.0","USER","40","60","UPS","SUB","CSO","9","54.0","379","0","0.0","Load on","--","0","72","Line Mode"]},{"realtime":true,"field":["72ce9335ea66ea610fa60c77d009ca8f","2023-08-24 18:36:43","92932010100438","235.9","50.3","219.8","1.1","0","0","0","235.9","50.3","448","404","8","Grid Tie","00075.04","230.0","23.9","48.0","230.0","23.9","50.0","5500","5500","46.0","56.4","54.0","USER","40","60","UPS","SUB","CSO","9","54.0","370","0","0.0","Load on","--","0","66","Line Mode"]},{"realtime":true,"field":["28465954c0683fbf2e91ec3372636ccf","2023-08-24 18:42:52","92932010100438","234.0","49.8","240.0","1.1","0","0","0","234.0","49.8","444","396","8","Grid Tie","00075.04","230.0","23.9","48.0","230.0","23.9","50.0","5500","5500","46.0","56.4","54.0","USER","40","60","UPS","SUB","CSO","9","54.0","367","0","0.0","Load on","--","0","53","Line Mode"]},{"realtime":true,"field":["56ff5cab6d6f98da2e3d248f4fe43f5b","2023-08-24 18:49:12","92932010100438","234.4","50.1","127.4","1.1","0","0","0","234.4","50.1","656","575","11","Grid Tie","00075.04","230.0","23.9","48.0","230.0","23.9","50.0","5500","5500","46.0","56.4","54.0","USER","40","60","UPS","SUB","CSO","9","54.0","368","0","0.0","Load on","--","0","29","Line Mode"]},{"realtime":true,"field":["20a63adbc678ca2052244b342489e378","2023-08-24 18:54:37","92932010100438","233.8","49.8","229.7","1.1","0","0","0","233.8","49.8","444","401","8","Grid Tie","00075.04","230.0","23.9","48.0","230.0","23.9","50.0","5500","5500","46.0","56.4","54.0","USER","40","60","UPS","SUB","CSO","9","54.0","367","0","0.0","Load on","--","0","45","Line Mode"]},{"realtime":true,"field":["57213a5273b6334d5eba8c5aa9079753","2023-08-24 19:00:42","92932010100438","232.7","50.1","164.3","1.1","0","0","0","232.7","50.1","628","582","11","Grid Tie","00075.04","230.0","23.9","48.0","230.0","23.9","50.0","5500","5500","46.0","56.4","54.0","USER","40","60","UPS","SUB","CSO","9","54.0","365","0","0.0","Load on","--","0","31","Line Mode"]},{"realtime":true,"field":["38ba36d37a00f2297a364e91544276cb","2023-08-24 19:06:15","92932010100438","231.2","49.8","121.8","1.1","0","0","0","231.2","49.8","624","573","11","Grid Tie","00075.04","230.0","23.9","48.0","230.0","23.9","50.0","5500","5500","46.0","56.4","54.0","USER","40","60","UPS","SUB","CSO","9","54.0","363","0","0.0","Load on","--","0","22","Line Mode"]},{"realtime":true,"field":["4eb5a48244e4bfd078adb39bf3396bc3","2023-08-24 19:12:29","92932010100438","230.4","50.0","0.0","1.1","0","0","0","230.4","50.0","668","643","12","Grid Tie","00075.04","230.0","23.9","48.0","230.0","23.9","50.0","5500","5500","46.0","56.4","54.0","USER","40","60","UPS","SUB","CSO","9","54.0","321","0","0.0","Load on","Do Nothing","0","0","Line Mode"]},{"realtime":true,"field":["7b24ac67d9802cdf5347595ed4ca598c","2023-08-24 19:18:17","92932010100438","229.8","49.9","0.0","1.1","0","0","0","229.8","49.9","643","611","11","Grid Tie","00075.04","230.0","23.9","48.0","230.0","23.9","50.0","5500","5500","46.0","56.4","54.0","USER","40","60","UPS","SUB","CSO","9","54.0","321","0","0.0","Load on","Do Nothing","0","0","Line Mode"]},{"realtime":true,"field":["24b564bc701fe8fd1303c052a0779926","2023-08-24 19:24:29","92932010100438","227.7","49.6","0.0","1.1","0","0","0","227.7","49.6","637","605","11","Grid Tie","00075.04","230.0","23.9","48.0","230.0","23.9","50.0","5500","5500","46.0","56.4","54.0","USER","40","60","UPS","SUB","CSO","9","54.0","319","0","0.0","Load on","Do Nothing","0","0","Line Mode"]},{"realtime":true,"field":["78b67199b1e0a08c7d33df34371a27f0","2023-08-24 19:30:20","92932010100438","228.6","49.9","0.0","1.1","0","0","0","228.6","49.9","640","596","11","Grid Tie","00075.04","230.0","23.9","48.0","230.0","23.9","50.0","5500","5500","46.0","56.4","54.0","USER","40","60","UPS","SUB","CSO","9","54.0","320","0","0.0","Load on","Do Nothing","0","0","Line Mode"]},{"realtime":true,"field":["47187720c29a0183257911999c631fbf","2023-08-24 19:36:42","92932010100438","226.6","50.1","0.0","1.1","0","0","0","226.6","50.1","611","582","11","Grid Tie","00075.04","230.0","23.9","48.0","230.0","23.9","50.0","5500","5500","46.0","56.4","54.0","USER","40","60","UPS","SUB","CSO","9","54.0","318","0","0.0","Load on","Do Nothing","0","0","Line Mode"]},{"realtime":true,"field":["19be10d0a0c0ccc9567b5ea7d976b46c","2023-08-24 19:42:22","92932010100438","226.5","50.3","0.0","1.1","0","0","0","226.5","50.3","611","585","11","Grid Tie","00075.04","230.0","23.9","48.0","230.0","23.9","50.0","5500","5500","46.0","56.4","54.0","USER","40","60","UPS","SUB","CSO","9","54.0","318","0","0.0","Load on","Do Nothing","0","0","Line Mode"]},{"realtime":true,"field":["5be0566d9d42d46c357edb9b033b95e6","2023-08-24 19:48:29","92932010100438","230.2","50.4","0.0","1.1","0","0","0","230.2","50.4","621","592","11","Grid Tie","00075.04","230.0","23.9","48.0","230.0","23.9","50.0","5500","5500","46.0","56.4","54.0","USER","40","60","UPS","SUB","CSO","9","54.0","322","0","0.0","Load on","Do Nothing","0","0","Line Mode"]},{"realtime":true,"field":["0142ce0a9b2fec8d0ea5c0afcf4e69b4","2023-08-24 19:53:50","92932010100438","230.4","50.3","0.0","1.1","0","0","0","230.4","50.3","622","593","11","Grid Tie","00075.04","230.0","23.9","48.0","230.0","23.9","50.0","5500","5500","46.0","56.4","54.0","USER","40","60","UPS","SUB","CSO","9","54.0","322","0","0.0","Load on","Do Nothing","0","0","Line Mode"]},{"realtime":true,"field":["76c46c734e27d2d90d0ffec4fe7312d2","2023-08-24 19:58:49","92932010100438","230.7","50.3","0.0","1.1","0","0","0","230.7","50.3","623","594","11","Grid Tie","00075.04","230.0","23.9","48.0","230.0","23.9","50.0","5500","5500","46.0","56.4","54.0","USER","40","60","UPS","SUB","CSO","9","54.0","323","0","0.0","Load on","Do Nothing","0","0","Line Mode"]},{"realtime":true,"field":["185501a777130d8d6a8bbcb8f71fe04c","2023-08-24 20:04:13","92932010100438","229.2","49.6","0.0","1.1","0","0","0","229.2","49.6","618","583","11","Grid Tie","00075.04","230.0","23.9","48.0","230.0","23.9","50.0","5500","5500","46.0","56.4","54.0","USER","40","60","UPS","SUB","CSO","9","54.0","321","0","0.0","Load on","Do Nothing","0","0","Line Mode"]},{"realtime":true,"field":["024e43f3097701280ea3801ad5634577","2023-08-24 20:09:17","92932010100438","230.2","50.2","0.0","1.1","0","0","0","230.2","50.2","621","593","11","Grid Tie","00075.04","230.0","23.9","48.0","230.0","23.9","50.0","5500","5500","46.0","56.4","54.0","USER","40","60","UPS","SUB","CSO","9","54.0","322","0","0.0","Load on","Do Nothing","0","0","Line Mode"]},{"realtime":true,"field":["66ef4fdd39de0ee36acf38e3af34ddda","2023-08-24 20:14:24","92932010100438","230.2","50.3","0.0","1.1","0","0","0","230.2","50.3","621","593","11","Grid Tie","00075.04","230.0","23.9","48.0","230.0","23.9","50.0","5500","5500","46.0","56.4","54.0","USER","40","60","UPS","SUB","CSO","9","54.0","323","0","0.0","Load on","Do Nothing","0","0","Line Mode"]},{"realtime":true,"field":["02a8954bd423edd62230aa5cbb654286","2023-08-24 20:19:32","92932010100438","229.9","50.4","0.0","1.1","0","0","0","229.9","50.4","620","591","11","Grid Tie","00075.04","230.0","23.9","48.0","230.0","23.9","50.0","5500","5500","46.0","56.4","54.0","USER","40","60","UPS","SUB","CSO","9","54.0","322","0","0.0","Load on","Do Nothing","0","0","Line Mode"]},{"realtime":true,"field":["0e2e64a131fafd3522f148df42b42cd0","2023-08-24 20:24:40","92932010100438","228.8","50.0","0.0","1.1","0","0","0","228.8","50.0","663","640","12","Grid Tie","00075.04","230.0","23.9","48.0","230.0","23.9","50.0","5500","5500","46.0","56.4","54.0","USER","40","60","UPS","SUB","CSO","9","54.0","321","0","0.0","Load on","Do Nothing","0","0","Line Mode"]},{"realtime":true,"field":["753ddb9aac7f6a5e297ad96b38a222ae","2023-08-24 20:30:06","92932010100438","227.8","49.8","0.0","1.1","0","0","0","227.8","49.8","660","623","12","Grid Tie","00075.04","230.0","23.9","48.0","230.0","23.9","50.0","5500","5500","46.0","56.4","54.0","USER","40","60","UPS","SUB","CSO","9","54.0","319","0","0.0","Load on","Do Nothing","0","0","Line Mode"]},{"realtime":true,"field":["00b6a62244c6dcda5f541f40a12ee340","2023-08-24 20:35:59","92932010100438","229.9","49.8","0.0","1.1","0","0","0","229.9","49.8","667","639","12","Grid Tie","00075.04","230.0","23.9","48.0","230.0","23.9","50.0","5500","5500","46.0","56.4","54.0","USER","40","60","UPS","SUB","CSO","9","54.0","323","0","0.0","Load on","Do Nothing","0","0","Line Mode"]},{"realtime":true,"field":["116fa42f6238e9f77d8e6f3a9750ddf1","2023-08-24 20:41:52","92932010100438","230.4","49.6","0.0","1.0","0","0","0","230.4","49.6","668","630","12","Grid Tie","00075.04","230.0","23.9","48.0","230.0","23.9","50.0","5500","5500","46.0","56.4","54.0","USER","40","60","UPS","SUB","CSO","9","54.0","323","0","0.0","Load on","Do Nothing","0","0","Line Mode"]},{"realtime":true,"field":["78a62818470be3b755f8be2d0226b509","2023-08-24 20:47:22","92932010100438","230.2","49.9","0.0","1.0","0","0","0","230.2","49.9","667","627","12","Grid Tie","00075.04","230.0","23.9","48.0","230.0","23.9","50.0","5500","5500","46.0","56.4","54.0","USER","40","60","UPS","SUB","CSO","9","54.0","323","0","0.0","Load on","Do Nothing","0","0","Line Mode"]},{"realtime":true,"field":["55919a05dce1b44a5b80ccbfbfbdbc60","2023-08-24 20:53:18","92932010100438","230.3","49.7","0.0","1.0","0","0","0","230.3","49.7","667","634","12","Grid Tie","00075.04","230.0","23.9","48.0","230.0","23.9","50.0","5500","5500","46.0","56.4","54.0","USER","40","60","UPS","SUB","CSO","9","54.0","323","0","0.0","Load on","Do Nothing","0","0","Line Mode"]},{"realtime":true,"field":["5764b97bcc8a2e81332fc8974cddf4a8","2023-08-24 20:58:47","92932010100438","230.4","50.0","0.0","1.0","0","0","0","230.4","50.0","668","643","12","Grid Tie","00075.04","230.0","23.9","48.0","230.0","23.9","50.0","5500","5500","46.0","56.4","54.0","USER","40","60","UPS","SUB","CSO","9","54.0","323","0","0.0","Load on","Do Nothing","0","0","Line Mode"]},{"realtime":true,"field":["3e63b69f581132bf34d8acc07b419a24","2023-08-24 21:04:42","92932010100438","230.4","49.9","0.0","1.0","0","0","0","230.4","49.9","552","529","10","Grid Tie","00075.04","230.0","23.9","48.0","230.0","23.9","50.0","5500","5500","46.0","56.4","54.0","USER","40","60","UPS","SUB","CSO","9","54.0","323","0","0.0","Load on","Do Nothing","0","0","Line Mode"]},{"realtime":true,"field":["5042fb5d6f85d86553ae9613452402b6","2023-08-24 21:10:24","92932010100438","229.3","49.9","0.0","1.0","0","0","0","229.3","49.9","596","560","10","Grid Tie","00075.04","230.0","23.9","48.0","230.0","23.9","50.0","5500","5500","46.0","56.4","54.0","USER","40","60","UPS","SUB","CSO","9","54.0","321","0","0.0","Load on","Do Nothing","0","0","Line Mode"]},{"realtime":true,"field":["31f92ecf8a781c4609693cb01e951d55","2023-08-24 21:16:08","92932010100438","229.6","49.9","0.0","1.0","0","0","0","229.6","49.9","711","675","12","Grid Tie","00075.04","230.0","23.9","48.0","230.0","23.9","50.0","5500","5500","46.0","56.4","54.0","USER","40","60","UPS","SUB","CSO","9","54.0","322","0","0.0","Load on","Do Nothing","0","0","Line Mode"]},{"realtime":true,"field":["31740014abc7fe6f2483627735532fd8","2023-08-24 21:21:43","92932010100438","230.4","50.2","0.0","1.0","0","0","0","230.4","50.2","645","604","11","Grid Tie","00075.04","230.0","23.9","48.0","230.0","23.9","50.0","5500","5500","46.0","56.4","54.0","USER","40","60","UPS","SUB","CSO","9","54.0","323","0","0.0","Load on","Do Nothing","0","0","Line Mode"]},{"realtime":true,"field":["204baf5771f2c36a5acb9fa93bb55cbc","2023-08-24 21:27:50","92932010100438","229.7","50.2","0.0","1.0","0","0","0","229.7","50.2","666","629","12","Grid Tie","00075.04","230.0","23.9","48.0","230.0","23.9","50.0","5500","5500","46.0","56.4","54.0","USER","40","60","UPS","SUB","CSO","9","54.0","322","0","0.0","Load on","Do Nothing","0","0","Line Mode"]},{"realtime":true,"field":["3b9368cdd3d3ec2b1bd7c5a67247ac3d","2023-08-24 21:33:26","92932010100438","229.0","50.1","0.0","1.0","0","0","0","229.0","50.1","641","601","11","Grid Tie","00075.04","230.0","23.9","48.0","230.0","23.9","50.0","5500","5500","46.0","56.4","54.0","USER","40","60","UPS","SUB","CSO","9","54.0","321","0","0.0","Load on","Do Nothing","0","0","Line Mode"]},{"realtime":true,"field":["7132c81d74f5222562145d0bc860f842","2023-08-24 21:39:32","92932010100438","228.1","49.9","0.0","1.0","0","0","0","228.1","49.9","661","622","12","Grid Tie","00075.04","230.0","23.9","48.0","230.0","23.9","50.0","5500","5500","46.0","56.4","54.0","USER","40","60","UPS","SUB","CSO","9","54.0","320","0","0.0","Load on","Do Nothing","0","0","Line Mode"]},{"realtime":true,"field":["040ed09dddbe7af025f4074051ad0872","2023-08-24 21:44:56","92932010100438","227.3","49.7","0.0","1.0","0","0","0","227.3","49.7","636","605","11","Grid Tie","00075.04","230.0","23.9","48.0","230.0","23.9","50.0","5500","5500","46.0","56.4","54.0","USER","40","60","UPS","SUB","CSO","9","54.0","318","0","0.0","Load on","Do Nothing","0","0","Line Mode"]},{"realtime":true,"field":["2ce6bdd50c0e65153ed8522ed245e09c","2023-08-24 21:49:52","92932010100438","226.7","49.8","0.0","1.0","0","0","0","226.7","49.8","634","600","11","Grid Tie","00075.04","230.0","23.9","48.0","230.0","23.9","50.0","5500","5500","46.0","56.4","54.0","USER","40","60","UPS","SUB","CSO","9","54.0","318","0","0.0","Load on","Do Nothing","0","0","Line Mode"]},{"realtime":true,"field":["723be4699776f81633e9081fb2693f34","2023-08-24 21:55:19","92932010100438","226.7","50.1","0.0","1.0","0","0","0","226.7","50.1","657","615","11","Grid Tie","00075.04","230.0","23.9","48.0","230.0","23.9","50.0","5500","5500","46.0","56.4","54.0","USER","40","60","UPS","SUB","CSO","9","54.0","319","0","0.0","Load on","Do Nothing","0","0","Line Mode"]},{"realtime":true,"field":["301b35d6442473ba605956c049a01a7f","2023-08-24 22:00:30","92932010100438","226.9","50.4","0.0","1.0","0","0","0","226.9","50.4","635","603","11","Grid Tie","00075.04","230.0","23.9","48.0","230.0","23.9","50.0","5500","5500","46.0","56.4","54.0","USER","40","60","UPS","SUB","CSO","9","54.0","319","0","0.0","Load on","Do Nothing","0","0","Line Mode"]},{"realtime":true,"field":["57064527c005b30f60dd38005f34756e","2023-08-24 22:05:36","92932010100438","227.6","50.3","0.0","1.0","0","0","0","227.6","50.3","682","645","12","Grid Tie","00075.04","230.0","23.9","48.0","230.0","23.9","50.0","5500","5500","46.0","56.4","54.0","USER","40","60","UPS","SUB","CSO","9","54.0","319","0","0.0","Load on","Do Nothing","0","0","Line Mode"]},{"realtime":true,"field":["149263602f4ae24375f53f84c43c0a34","2023-08-24 22:10:37","92932010100438","226.2","50.0","0.0","1.0","0","0","0","226.2","50.0","655","623","11","Grid Tie","00075.04","230.0","23.9","48.0","230.0","23.9","50.0","5500","5500","46.0","56.4","54.0","USER","40","60","UPS","SUB","CSO","9","54.0","317","0","0.0","Load on","Do Nothing","0","0","Line Mode"]},{"realtime":true,"field":["47de232b62a2c3d54c5abe419670d85d","2023-08-24 22:15:40","92932010100438","225.4","50.2","0.0","1.0","0","0","0","225.4","50.2","676","636","12","Grid Tie","00075.04","230.0","23.9","48.0","230.0","23.9","50.0","5500","5500","46.0","56.4","54.0","USER","40","60","UPS","SUB","CSO","9","54.0","317","0","0.0","Load on","Do Nothing","0","0","Line Mode"]},{"realtime":true,"field":["5365cf80c5d97aca6c603408bf8f0ca6","2023-08-24 22:20:39","92932010100438","225.2","50.0","0.0","1.0","0","0","0","225.2","50.0","653","617","11","Grid Tie","00075.04","230.0","23.9","48.0","230.0","23.9","50.0","5500","5500","46.0","56.4","54.0","USER","40","60","UPS","SUB","CSO","9","54.0","316","0","0.0","Load on","Do Nothing","0","0","Line Mode"]},{"realtime":true,"field":["5625eb9c889ff662348430329879c5b8","2023-08-24 22:25:50","92932010100438","225.4","50.0","0.0","1.0","0","0","0","225.4","50.0","675","640","12","Grid Tie","00075.04","230.0","23.9","48.0","230.0","23.9","50.0","5500","5500","46.0","56.4","54.0","USER","40","60","UPS","SUB","CSO","9","54.0","316","0","0.0","Load on","Do Nothing","0","0","Line Mode"]},{"realtime":true,"field":["6acf57a817a0c6291af6cbc646bbd5f3","2023-08-24 22:32:06","92932010100438","224.7","50.4","0.0","1.0","0","0","0","224.7","50.4","651","608","11","Grid Tie","00075.04","230.0","23.9","48.0","230.0","23.9","50.0","5500","5500","46.0","56.4","54.0","USER","40","60","UPS","SUB","CSO","9","54.0","313","0","0.0","Load on","Do Nothing","0","0","Line Mode"]},{"realtime":true,"field":["1df5ac3fe7db248c177abdbad37105d4","2023-08-24 22:38:10","92932010100438","224.6","50.2","0.0","1.0","0","0","0","224.6","50.2","651","624","11","Grid Tie","00075.04","230.0","23.9","48.0","230.0","23.9","50.0","5500","5500","46.0","56.4","54.0","USER","40","60","UPS","SUB","CSO","9","54.0","313","0","0.0","Load on","Do Nothing","0","0","Line Mode"]},{"realtime":true,"field":["458e707dee473fe745f5fb4efafb89fb","2023-08-24 22:44:10","92932010100438","227.0","50.3","0.0","1.0","0","0","0","227.0","50.3","658","623","11","Grid Tie","00075.04","230.0","23.9","48.0","230.0","23.9","50.0","5500","5500","46.0","56.4","54.0","USER","40","60","UPS","SUB","CSO","9","54.0","316","0","0.0","Load on","Do Nothing","0","0","Line Mode"]},{"realtime":true,"field":["6f685c6f6959414a6c83bbe03c833eef","2023-08-24 22:50:14","92932010100438","223.4","50.3","0.0","1.0","0","0","0","223.4","50.3","2345","2312","42","Grid Tie","00075.04","230.0","23.9","48.0","230.0","23.9","50.0","5500","5500","46.0","56.4","54.0","USER","40","60","UPS","SUB","CSO","9","54.0","311","0","0.0","Load on","Do Nothing","0","0","Line Mode"]},{"realtime":true,"field":["518c5ff1ba0f99ca4ba57a058c8d41cb","2023-08-24 22:56:36","92932010100438","223.5","50.3","0.0","1.0","0","0","0","223.5","50.3","2369","2366","43","Grid Tie","00075.04","230.0","23.9","48.0","230.0","23.9","50.0","5500","5500","46.0","56.4","54.0","USER","40","60","UPS","SUB","CSO","9","54.0","311","0","0.0","Load on","Do Nothing","0","0","Line Mode"]},{"realtime":true,"field":["3f990f9fdfaa7ad16661c93e6b7d1198","2023-08-24 23:03:06","92932010100438","223.1","50.1","0.0","1.0","0","0","0","223.1","50.1","2298","2298","41","Grid Tie","00075.04","230.0","23.9","48.0","230.0","23.9","50.0","5500","5500","46.0","56.4","54.0","USER","40","60","UPS","SUB","CSO","9","54.0","311","0","0.0","Load on","Do Nothing","0","0","Line Mode"]},{"realtime":true,"field":["3d504f5e0864febf2b6e22e62a436471","2023-08-24 23:09:19","92932010100438","222.4","49.9","0.0","1.0","0","0","0","222.4","49.9","1945","1945","35","Grid Tie","00075.04","230.0","23.9","48.0","230.0","23.9","50.0","5500","5500","46.0","56.4","54.0","USER","40","60","UPS","SUB","CSO","9","54.0","310","0","0.0","Load on","Do Nothing","0","0","Line Mode"]},{"realtime":true,"field":["516af463ced286d971ce9de4f886b097","2023-08-24 23:15:43","92932010100438","223.3","50.1","0.0","1.0","0","0","0","223.3","50.1","1697","1696","30","Grid Tie","00075.04","230.0","23.9","48.0","230.0","23.9","50.0","5500","5500","46.0","56.4","54.0","USER","40","60","UPS","SUB","CSO","9","54.0","311","0","0.0","Load on","Do Nothing","0","0","Line Mode"]},{"realtime":true,"field":["747043c84d6a7e957e19aff27609fe40","2023-08-24 23:22:55","92932010100438","225.0","50.0","0.0","1.0","0","0","0","225.0","50.0","1228","1228","22","Grid Tie","00075.04","230.0","23.9","48.0","230.0","23.9","50.0","5500","5500","46.0","56.4","54.0","USER","40","60","UPS","SUB","CSO","9","54.0","314","0","0.0","Load on","Do Nothing","0","0","Line Mode"]},{"realtime":true,"field":["282bb2ccde49fa6e122f681c89984a19","2023-08-24 23:29:12","92932010100438","224.0","50.2","0.0","1.0","0","0","0","224.0","50.2","1330","1330","24","Grid Tie","00075.04","230.0","23.9","48.0","230.0","23.9","50.0","5500","5500","46.0","56.4","54.0","USER","40","60","UPS","SUB","CSO","9","54.0","313","0","0.0","Load on","Do Nothing","0","0","Line Mode"]},{"realtime":true,"field":["63547040663f8b4e6c741034f7487400","2023-08-24 23:34:56","92932010100438","227.2","49.9","0.0","1.0","0","0","0","227.2","49.9","1227","1217","22","Grid Tie","00075.04","230.0","23.9","48.0","230.0","23.9","50.0","5500","5500","46.0","56.4","54.0","USER","40","60","UPS","SUB","CSO","9","54.0","317","0","0.0","Load on","Do Nothing","0","0","Line Mode"]},{"realtime":true,"field":["7754ec1c4ea97d4911f2010a577b38e9","2023-08-24 23:40:28","92932010100438","228.1","50.0","0.0","1.0","0","0","0","228.1","50.0","1208","1201","21","Grid Tie","00075.04","230.0","23.9","48.0","230.0","23.9","50.0","5500","5500","46.0","56.4","54.0","USER","40","60","UPS","SUB","CSO","9","54.0","318","0","0.0","Load on","Do Nothing","0","0","Line Mode"]},{"realtime":true,"field":["45511f7e750489cb465c9fbe559fad1d","2023-08-24 23:45:31","92932010100438","229.1","50.1","0.0","1.0","0","0","0","229.1","50.1","1108","1108","20","Grid Tie","00075.04","230.0","23.9","48.0","230.0","23.9","50.0","5500","5500","46.0","56.4","54.0","USER","40","60","UPS","SUB","CSO","9","54.0","320","0","0.0","Load on","Do Nothing","0","0","Line Mode"]},{"realtime":true,"field":["65e658894595adde020b98e733160cd3","2023-08-24 23:50:32","92932010100438","227.3","49.8","0.0","1.0","0","0","0","227.3","49.8","1220","1220","22","Grid Tie","00075.04","230.0","23.9","48.0","230.0","23.9","50.0","5500","5500","46.0","56.4","54.0","USER","40","60","UPS","SUB","CSO","9","54.0","317","0","0.0","Load on","Do Nothing","0","0","Line Mode"]},{"realtime":true,"field":["2f15502d25c518485f471e80b379c590","2023-08-24 23:55:34","92932010100438","227.9","49.8","0.0","1.0","0","0","0","227.9","49.8","1162","1156","21","Grid Tie","00075.04","230.0","23.9","48.0","230.0","23.9","50.0","5500","5500","46.0","56.4","54.0","USER","40","60","UPS","SUB","CSO","9","54.0","318","0","0.0","Load on","Do Nothing","0","0","Line Mode"]}]}}